{"resourceType": "Bundle", "type": "transaction", "entry": [{"fullUrl": "urn:uuid:1b179b16-266c-44b6-87ec-2055f7b4fd72", "resource": {"resourceType": "Basic", "id": "1b179b16-266c-44b6-87ec-2055f7b4fd72", "meta": {"profile": ["http://standardhealthrecord.org/fhir/StructureDefinition/shr-entity-Person"]}, "code": {"coding": [{"system": "http://standardhealthrecord.org/fhir/basic-resource-type", "code": "shr-entity-Person", "display": "shr-entity-Person"}]}}, "request": {"method": "POST", "url": "Basic"}}, {"fullUrl": "urn:uuid:3ed64677-8b2c-440c-a593-aa0e00ac2018", "resource": {"resourceType": "Patient", "id": "3ed64677-8b2c-440c-a593-aa0e00ac2018", "meta": {"profile": ["http://standardhealthrecord.org/fhir/StructureDefinition/shr-entity-Patient"]}, "extension": [{"url": "http://hl7.org/fhir/us/core/StructureDefinition/us-core-race", "extension": [{"url": "ombCategory", "valueCoding": {"system": "urn:oid:2.16.840.1.113883.6.238", "code": "2106-3", "display": "White"}}, {"url": "text", "valueString": "White"}]}, {"url": "http://hl7.org/fhir/us/core/StructureDefinition/us-core-ethnicity", "extension": [{"url": "ombCategory", "valueCoding": {"system": "urn:oid:2.16.840.1.113883.6.238", "code": "2186-5", "display": "Not Hispanic or Latino"}}, {"url": "text", "valueString": "Not Hispanic or Latino"}]}, {"url": "http://hl7.org/fhir/StructureDefinition/patient-mothersMaidenName", "valueString": "Windy313 Johnson679"}, {"url": "http://hl7.org/fhir/us/core/StructureDefinition/us-core-birthsex", "valueCode": "M"}, {"url": "http://hl7.org/fhir/StructureDefinition/birthPlace", "valueAddress": {"city": "Walpole", "state": "Massachusetts", "country": "US"}}, {"url": "http://standardhealthrecord.org/fhir/StructureDefinition/shr-actor-FictionalPerson-extension", "valueBoolean": true}, {"url": "http://standardhealthrecord.org/fhir/StructureDefinition/shr-entity-FathersName-extension", "valueHumanName": {"text": "Von197 Ruecker817"}}, {"url": "http://standardhealthrecord.org/fhir/StructureDefinition/shr-demographics-SocialSecurityNumber-extension", "valueString": "999-34-6683"}, {"url": "http://standardhealthrecord.org/fhir/StructureDefinition/shr-entity-Person-extension", "valueReference": {"reference": "urn:uuid:1b179b16-266c-44b6-87ec-2055f7b4fd72"}}, {"url": "http://synthetichealth.github.io/synthea/disability-adjusted-life-years", "valueDecimal": 0.7730839906592617}, {"url": "http://synthetichealth.github.io/synthea/quality-adjusted-life-years", "valueDecimal": 34.22691600934074}], "identifier": [{"system": "https://github.com/synthetichealth/synthea", "value": "3b8276e7-a036-4851-a3a4-ba64a88ece0a"}, {"type": {"coding": [{"system": "http://hl7.org/fhir/v2/0203", "code": "MR", "display": "Medical Record Number"}], "text": "Medical Record Number"}, "system": "http://hospital.smarthealthit.org", "value": "3b8276e7-a036-4851-a3a4-ba64a88ece0a"}, {"type": {"coding": [{"system": "http://hl7.org/fhir/identifier-type", "code": "SB", "display": "Social Security Number"}], "text": "Social Security Number"}, "system": "http://hl7.org/fhir/sid/us-ssn", "value": "999-34-6683"}, {"type": {"coding": [{"system": "http://hl7.org/fhir/v2/0203", "code": "DL", "display": "Driver's License"}], "text": "Driver's License"}, "system": "urn:oid:2.16.840.1.113883.4.3.25", "value": "S99941055"}, {"type": {"coding": [{"system": "http://hl7.org/fhir/v2/0203", "code": "PPN", "display": "Passport Number"}], "text": "Passport Number"}, "system": "http://standardhealthrecord.org/fhir/StructureDefinition/passportNumber", "value": "X53307305X"}], "name": [{"use": "official", "family": "Ruecker817", "given": ["Noble66"], "prefix": ["Mr."]}], "telecom": [{"system": "phone", "value": "555-150-1378", "use": "home"}], "gender": "male", "birthDate": "1982-03-16", "address": [{"extension": [{"url": "http://hl7.org/fhir/StructureDefinition/geolocation", "extension": [{"url": "latitude", "valueDecimal": -72.539978}, {"url": "longitude", "valueDecimal": 42.115454}]}], "line": ["288 Pfannerstill Run"], "city": "Springfield", "state": "Massachusetts", "postalCode": "01013", "country": "US"}], "maritalStatus": {"coding": [{"system": "http://hl7.org/fhir/v3/MaritalStatus", "code": "M", "display": "M"}], "text": "M"}, "multipleBirthBoolean": false, "communication": [{"language": {"coding": [{"system": "urn:ietf:bcp:47", "code": "en-US", "display": "English"}], "text": "English"}}]}, "request": {"method": "POST", "url": "Patient"}}, {"fullUrl": "urn:uuid:609c86d7-5324-477b-99a2-b1608551ef1f", "resource": {"resourceType": "Organization", "id": "609c86d7-5324-477b-99a2-b1608551ef1f", "meta": {"profile": ["http://standardhealthrecord.org/fhir/StructureDefinition/shr-entity-Organization"]}, "identifier": [{"system": "https://github.com/synthetichealth/synthea", "value": "430bcdbc-7a45-482a-96ce-b798a3132bd4"}, {"system": "urn:ietf:rfc:3986", "value": "430bcdbc-7a45-482a-96ce-b798a3132bd4"}], "type": [{"coding": [{"system": "Healthcare Provider", "code": "prov", "display": "Healthcare Provider"}], "text": "Healthcare Provider"}], "name": "MERCY MEDICAL CTR", "telecom": [{"system": "phone", "value": "4137489000"}], "address": [{"line": ["271 CAREW STREET"], "city": "SPRINGFIELD", "state": "MA", "postalCode": "01104", "country": "US"}], "contact": [{"name": {"text": "Synthetic Provider"}}]}, "request": {"method": "POST", "url": "Organization"}}, {"fullUrl": "urn:uuid:6e7b19bb-64de-4617-8e45-bfc5a66768bf", "resource": {"resourceType": "Encounter", "id": "6e7b19bb-64de-4617-8e45-bfc5a66768bf", "meta": {"profile": ["http://standardhealthrecord.org/fhir/StructureDefinition/shr-encounter-EncounterPerformed"]}, "extension": [{"url": "http://standardhealthrecord.org/fhir/StructureDefinition/shr-action-PerformedContext-extension", "extension": [{"url": "http://standardhealthrecord.org/fhir/StructureDefinition/shr-action-Status-extension", "valueCode": "finished"}]}], "status": "finished", "class": {"code": "WELLNESS"}, "type": [{"coding": [{"system": "http://snomed.info/sct", "code": "185349003", "display": "Encounter for check up (procedure)"}], "text": "Encounter for check up (procedure)"}], "subject": {"reference": "urn:uuid:3ed64677-8b2c-440c-a593-aa0e00ac2018"}, "period": {"start": "2007-05-22T13:19:17+08:00", "end": "2007-05-22T13:49:17+08:00"}, "serviceProvider": {"reference": "urn:uuid:609c86d7-5324-477b-99a2-b1608551ef1f"}}, "request": {"method": "POST", "url": "Encounter"}}, {"fullUrl": "urn:uuid:24f4dc69-adba-4fc3-b3bc-c823d6367569", "resource": {"resourceType": "Condition", "id": "24f4dc69-adba-4fc3-b3bc-c823d6367569", "meta": {"profile": ["http://standardhealthrecord.org/fhir/StructureDefinition/shr-condition-Condition"]}, "clinicalStatus": "active", "verificationStatus": "confirmed", "category": [{"coding": [{"system": "http://standardhealthrecord.org/shr/condition/vs/ConditionCategoryVS", "code": "disease", "display": "Disease"}]}], "code": {"coding": [{"system": "http://snomed.info/sct", "code": "15777000", "display": "Prediabetes"}], "text": "Prediabetes"}, "subject": {"reference": "urn:uuid:3ed64677-8b2c-440c-a593-aa0e00ac2018"}, "context": {"reference": "urn:uuid:6e7b19bb-64de-4617-8e45-bfc5a66768bf"}, "onsetDateTime": "2007-05-22T13:19:17+08:00", "assertedDate": "2007-05-22T13:19:17+08:00"}, "request": {"method": "POST", "url": "Condition"}}, {"fullUrl": "urn:uuid:be666652-1a68-42a7-9da8-d646b31d24cf", "resource": {"resourceType": "Goal", "id": "be666652-1a68-42a7-9da8-d646b31d24cf", "status": "in-progress", "description": {"text": "Hemoglobin A1c total in Blood < 7.0"}}, "request": {"method": "POST", "url": "Goal"}}, {"fullUrl": "urn:uuid:1fd59ef1-c325-45da-b5e3-06fb714675e9", "resource": {"resourceType": "Goal", "id": "1fd59ef1-c325-45da-b5e3-06fb714675e9", "status": "in-progress", "description": {"text": "Glucose [Mass/volume] in Blood < 108"}}, "request": {"method": "POST", "url": "Goal"}}, {"fullUrl": "urn:uuid:a5daa48b-489a-453b-8963-a10310b87efd", "resource": {"resourceType": "Goal", "id": "a5daa48b-489a-453b-8963-a10310b87efd", "status": "in-progress", "description": {"text": "Maintain blood pressure below 140/90 mmHg"}}, "request": {"method": "POST", "url": "Goal"}}, {"fullUrl": "urn:uuid:0108d8af-78ea-47b8-b3cc-e8846cba156d", "resource": {"resourceType": "Goal", "id": "0108d8af-78ea-47b8-b3cc-e8846cba156d", "status": "in-progress", "description": {"text": "Improve and maintenance of optimal foot health: aim at early detection of peripheral vascular problems and neuropathy presumed due to diabetes; and prevention of diabetic foot ulcer, gangrene"}}, "request": {"method": "POST", "url": "Goal"}}, {"fullUrl": "urn:uuid:021d851f-c633-468b-8fc0-19420f37f0f0", "resource": {"resourceType": "Goal", "id": "021d851f-c633-468b-8fc0-19420f37f0f0", "status": "in-progress", "description": {"text": "Address patient knowledge deficit on diabetic self-care"}}, "request": {"method": "POST", "url": "Goal"}}, {"fullUrl": "urn:uuid:bb8f08e0-ae64-4a31-ab3e-bee2d3889ca1", "resource": {"resourceType": "CarePlan", "id": "bb8f08e0-ae64-4a31-ab3e-bee2d3889ca1", "status": "active", "intent": "order", "category": [{"coding": [{"system": "http://snomed.info/sct", "code": "698360004", "display": "Diabetes self management plan"}], "text": "Diabetes self management plan"}], "subject": {"reference": "urn:uuid:3ed64677-8b2c-440c-a593-aa0e00ac2018"}, "context": {"reference": "urn:uuid:6e7b19bb-64de-4617-8e45-bfc5a66768bf"}, "period": {"start": "2007-05-22T13:19:17+08:00"}, "addresses": [{"reference": "urn:uuid:24f4dc69-adba-4fc3-b3bc-c823d6367569"}], "goal": [{"reference": "urn:uuid:be666652-1a68-42a7-9da8-d646b31d24cf"}, {"reference": "urn:uuid:1fd59ef1-c325-45da-b5e3-06fb714675e9"}, {"reference": "urn:uuid:a5daa48b-489a-453b-8963-a10310b87efd"}, {"reference": "urn:uuid:0108d8af-78ea-47b8-b3cc-e8846cba156d"}, {"reference": "urn:uuid:021d851f-c633-468b-8fc0-19420f37f0f0"}], "activity": [{"detail": {"code": {"coding": [{"system": "http://snomed.info/sct", "code": "160670007", "display": "Diabetic diet"}], "text": "Diabetic diet"}, "status": "in-progress"}}, {"detail": {"code": {"coding": [{"system": "http://snomed.info/sct", "code": "229065009", "display": "Exercise therapy"}], "text": "Exercise therapy"}, "status": "in-progress"}}]}, "request": {"method": "POST", "url": "CarePlan"}}, {"fullUrl": "urn:uuid:96f3f947-82e0-49a3-a6fc-823d611f25ef", "resource": {"resourceType": "Claim", "id": "96f3f947-82e0-49a3-a6fc-823d611f25ef", "status": "active", "use": "complete", "patient": {"reference": "urn:uuid:3ed64677-8b2c-440c-a593-aa0e00ac2018"}, "billablePeriod": {"start": "2007-05-22T13:19:17+08:00", "end": "2007-05-22T13:49:17+08:00"}, "organization": {"reference": "urn:uuid:609c86d7-5324-477b-99a2-b1608551ef1f"}, "diagnosis": [{"sequence": 1, "diagnosisReference": {"reference": "urn:uuid:24f4dc69-adba-4fc3-b3bc-c823d6367569"}}], "item": [{"sequence": 1, "encounter": [{"reference": "urn:uuid:6e7b19bb-64de-4617-8e45-bfc5a66768bf"}]}, {"sequence": 2, "diagnosisLinkId": [1]}], "total": {"value": 125.0, "system": "urn:iso:std:iso:4217", "code": "USD"}}, "request": {"method": "POST", "url": "Claim"}}, {"fullUrl": "urn:uuid:f7de259c-0b6f-402f-a49f-bc8d9c3204f3", "resource": {"resourceType": "Encounter", "id": "f7de259c-0b6f-402f-a49f-bc8d9c3204f3", "meta": {"profile": ["http://standardhealthrecord.org/fhir/StructureDefinition/shr-encounter-EncounterPerformed"]}, "extension": [{"url": "http://standardhealthrecord.org/fhir/StructureDefinition/shr-action-PerformedContext-extension", "extension": [{"url": "http://standardhealthrecord.org/fhir/StructureDefinition/shr-action-Status-extension", "valueCode": "finished"}]}], "status": "finished", "class": {"code": "WELLNESS"}, "type": [{"coding": [{"system": "http://snomed.info/sct", "code": "185349003", "display": "Encounter for check up (procedure)"}], "text": "Encounter for check up (procedure)"}], "subject": {"reference": "urn:uuid:3ed64677-8b2c-440c-a593-aa0e00ac2018"}, "period": {"start": "2010-05-25T13:19:17+08:00", "end": "2010-05-25T13:34:17+08:00"}, "serviceProvider": {"reference": "urn:uuid:609c86d7-5324-477b-99a2-b1608551ef1f"}}, "request": {"method": "POST", "url": "Encounter"}}, {"fullUrl": "urn:uuid:374bbaaa-daff-4651-b51c-7deb2c00d6af", "resource": {"resourceType": "Observation", "id": "374bbaaa-daff-4651-b51c-7deb2c00d6af", "meta": {"profile": ["http://standardhealthrecord.org/fhir/StructureDefinition/shr-finding-Observation", "http://standardhealthrecord.org/fhir/StructureDefinition/shr-vital-VitalSign", "http://standardhealthrecord.org/fhir/StructureDefinition/shr-vital-BodyHeight"]}, "status": "final", "category": [{"coding": [{"system": "http://hl7.org/fhir/observation-category", "code": "vital-signs", "display": "vital-signs"}]}], "code": {"coding": [{"system": "http://loinc.org", "code": "8302-2", "display": "Body Height"}], "text": "Body Height"}, "subject": {"reference": "urn:uuid:3ed64677-8b2c-440c-a593-aa0e00ac2018"}, "context": {"reference": "urn:uuid:f7de259c-0b6f-402f-a49f-bc8d9c3204f3"}, "effectiveDateTime": "2010-05-25T13:19:17+08:00", "issued": "2010-05-25T13:19:17.553+08:00", "valueQuantity": {"value": 173.5779130511357, "unit": "cm", "system": "http://unitsofmeasure.org", "code": "cm"}}, "request": {"method": "POST", "url": "Observation"}}, {"fullUrl": "urn:uuid:14f9f678-9838-4eef-a85e-0d944c728c11", "resource": {"resourceType": "Observation", "id": "14f9f678-9838-4eef-a85e-0d944c728c11", "meta": {"profile": ["http://standardhealthrecord.org/fhir/StructureDefinition/shr-finding-Observation", "http://standardhealthrecord.org/fhir/StructureDefinition/shr-vital-VitalSign", "http://standardhealthrecord.org/fhir/StructureDefinition/shr-vital-BodyWeight"]}, "status": "final", "category": [{"coding": [{"system": "http://hl7.org/fhir/observation-category", "code": "vital-signs", "display": "vital-signs"}]}], "code": {"coding": [{"system": "http://loinc.org", "code": "29463-7", "display": "Body Weight"}], "text": "Body Weight"}, "subject": {"reference": "urn:uuid:3ed64677-8b2c-440c-a593-aa0e00ac2018"}, "context": {"reference": "urn:uuid:f7de259c-0b6f-402f-a49f-bc8d9c3204f3"}, "effectiveDateTime": "2010-05-25T13:19:17+08:00", "issued": "2010-05-25T13:19:17.553+08:00", "valueQuantity": {"value": 82.36145661258392, "unit": "kg", "system": "http://unitsofmeasure.org", "code": "kg"}}, "request": {"method": "POST", "url": "Observation"}}, {"fullUrl": "urn:uuid:a1475f8f-5a15-46ec-b947-e155b77e17ad", "resource": {"resourceType": "Observation", "id": "a1475f8f-5a15-46ec-b947-e155b77e17ad", "meta": {"profile": ["http://standardhealthrecord.org/fhir/StructureDefinition/shr-finding-Observation", "http://standardhealthrecord.org/fhir/StructureDefinition/shr-vital-VitalSign", "http://standardhealthrecord.org/fhir/StructureDefinition/shr-vital-BodyMassIndex"]}, "status": "final", "category": [{"coding": [{"system": "http://hl7.org/fhir/observation-category", "code": "vital-signs", "display": "vital-signs"}]}], "code": {"coding": [{"system": "http://loinc.org", "code": "39156-5", "display": "Body Mass Index"}], "text": "Body Mass Index"}, "subject": {"reference": "urn:uuid:3ed64677-8b2c-440c-a593-aa0e00ac2018"}, "context": {"reference": "urn:uuid:f7de259c-0b6f-402f-a49f-bc8d9c3204f3"}, "effectiveDateTime": "2010-05-25T13:19:17+08:00", "issued": "2010-05-25T13:19:17.553+08:00", "valueQuantity": {"value": 27.336008057595482, "unit": "kg/m2", "system": "http://unitsofmeasure.org", "code": "kg/m2"}}, "request": {"method": "POST", "url": "Observation"}}, {"fullUrl": "urn:uuid:1f4b42c9-250b-48bd-8c82-f3470d1e4bd5", "resource": {"resourceType": "Observation", "id": "1f4b42c9-250b-48bd-8c82-f3470d1e4bd5", "meta": {"profile": ["http://standardhealthrecord.org/fhir/StructureDefinition/shr-finding-Observation", "http://standardhealthrecord.org/fhir/StructureDefinition/shr-vital-VitalSign", "http://standardhealthrecord.org/fhir/StructureDefinition/shr-vital-BloodPressure"]}, "status": "final", "category": [{"coding": [{"system": "http://hl7.org/fhir/observation-category", "code": "vital-signs", "display": "vital-signs"}]}], "code": {"coding": [{"system": "http://loinc.org", "code": "55284-4", "display": "Blood Pressure"}], "text": "Blood Pressure"}, "subject": {"reference": "urn:uuid:3ed64677-8b2c-440c-a593-aa0e00ac2018"}, "context": {"reference": "urn:uuid:f7de259c-0b6f-402f-a49f-bc8d9c3204f3"}, "effectiveDateTime": "2010-05-25T13:19:17+08:00", "issued": "2010-05-25T13:19:17.553+08:00", "component": [{"code": {"coding": [{"system": "http://loinc.org", "code": "8462-4", "display": "Diastolic Blood Pressure"}], "text": "Diastolic Blood Pressure"}, "valueQuantity": {"value": 88.05907632939878, "unit": "mmHg", "system": "http://unitsofmeasure.org", "code": "mmHg"}}, {"code": {"coding": [{"system": "http://loinc.org", "code": "8480-6", "display": "Systolic Blood Pressure"}], "text": "Systolic Blood Pressure"}, "valueQuantity": {"value": 121.81728034050323, "unit": "mmHg", "system": "http://unitsofmeasure.org", "code": "mmHg"}}]}, "request": {"method": "POST", "url": "Observation"}}, {"fullUrl": "urn:uuid:54ff1368-c285-40f6-a9f0-da1f83924586", "resource": {"resourceType": "Observation", "id": "54ff1368-c285-40f6-a9f0-da1f83924586", "meta": {"profile": ["http://standardhealthrecord.org/fhir/StructureDefinition/shr-finding-Observation"]}, "status": "final", "category": [{"coding": [{"system": "http://hl7.org/fhir/observation-category", "code": "laboratory", "display": "laboratory"}]}], "code": {"coding": [{"system": "http://loinc.org", "code": "2339-0", "display": "Glucose"}], "text": "Glucose"}, "subject": {"reference": "urn:uuid:3ed64677-8b2c-440c-a593-aa0e00ac2018"}, "context": {"reference": "urn:uuid:f7de259c-0b6f-402f-a49f-bc8d9c3204f3"}, "effectiveDateTime": "2010-05-25T13:19:17+08:00", "issued": "2010-05-25T13:19:17.553+08:00", "valueQuantity": {"value": 66.0903777947367, "unit": "mg/dL", "system": "http://unitsofmeasure.org", "code": "mg/dL"}}, "request": {"method": "POST", "url": "Observation"}}, {"fullUrl": "urn:uuid:5382ed08-bd70-4a45-ab80-db125802f2ce", "resource": {"resourceType": "Observation", "id": "5382ed08-bd70-4a45-ab80-db125802f2ce", "meta": {"profile": ["http://standardhealthrecord.org/fhir/StructureDefinition/shr-finding-Observation"]}, "status": "final", "category": [{"coding": [{"system": "http://hl7.org/fhir/observation-category", "code": "laboratory", "display": "laboratory"}]}], "code": {"coding": [{"system": "http://loinc.org", "code": "6299-2", "display": "Urea Nitrogen"}], "text": "Urea Nitrogen"}, "subject": {"reference": "urn:uuid:3ed64677-8b2c-440c-a593-aa0e00ac2018"}, "context": {"reference": "urn:uuid:f7de259c-0b6f-402f-a49f-bc8d9c3204f3"}, "effectiveDateTime": "2010-05-25T13:19:17+08:00", "issued": "2010-05-25T13:19:17.553+08:00", "valueQuantity": {"value": 17.788415349730364, "unit": "mg/dL", "system": "http://unitsofmeasure.org", "code": "mg/dL"}}, "request": {"method": "POST", "url": "Observation"}}, {"fullUrl": "urn:uuid:4bb09f51-2dd0-4903-8d43-f430cf6d8f7f", "resource": {"resourceType": "Observation", "id": "4bb09f51-2dd0-4903-8d43-f430cf6d8f7f", "meta": {"profile": ["http://standardhealthrecord.org/fhir/StructureDefinition/shr-finding-Observation"]}, "status": "final", "category": [{"coding": [{"system": "http://hl7.org/fhir/observation-category", "code": "laboratory", "display": "laboratory"}]}], "code": {"coding": [{"system": "http://loinc.org", "code": "38483-4", "display": "Creatinine"}], "text": "Creatinine"}, "subject": {"reference": "urn:uuid:3ed64677-8b2c-440c-a593-aa0e00ac2018"}, "context": {"reference": "urn:uuid:f7de259c-0b6f-402f-a49f-bc8d9c3204f3"}, "effectiveDateTime": "2010-05-25T13:19:17+08:00", "issued": "2010-05-25T13:19:17.553+08:00", "valueQuantity": {"value": 1.5649277708235905, "unit": "mg/dL", "system": "http://unitsofmeasure.org", "code": "mg/dL"}}, "request": {"method": "POST", "url": "Observation"}}, {"fullUrl": "urn:uuid:6f03c7aa-caf4-4cd7-af65-6b6ddf31beb5", "resource": {"resourceType": "Observation", "id": "6f03c7aa-caf4-4cd7-af65-6b6ddf31beb5", "meta": {"profile": ["http://standardhealthrecord.org/fhir/StructureDefinition/shr-finding-Observation"]}, "status": "final", "category": [{"coding": [{"system": "http://hl7.org/fhir/observation-category", "code": "laboratory", "display": "laboratory"}]}], "code": {"coding": [{"system": "http://loinc.org", "code": "49765-1", "display": "Calcium"}], "text": "Calcium"}, "subject": {"reference": "urn:uuid:3ed64677-8b2c-440c-a593-aa0e00ac2018"}, "context": {"reference": "urn:uuid:f7de259c-0b6f-402f-a49f-bc8d9c3204f3"}, "effectiveDateTime": "2010-05-25T13:19:17+08:00", "issued": "2010-05-25T13:19:17.553+08:00", "valueQuantity": {"value": 9.727778448466657, "unit": "mg/dL", "system": "http://unitsofmeasure.org", "code": "mg/dL"}}, "request": {"method": "POST", "url": "Observation"}}, {"fullUrl": "urn:uuid:84ddc0dd-5394-4da2-a54e-e8a620b8d464", "resource": {"resourceType": "Observation", "id": "84ddc0dd-5394-4da2-a54e-e8a620b8d464", "meta": {"profile": ["http://standardhealthrecord.org/fhir/StructureDefinition/shr-finding-Observation"]}, "status": "final", "category": [{"coding": [{"system": "http://hl7.org/fhir/observation-category", "code": "laboratory", "display": "laboratory"}]}], "code": {"coding": [{"system": "http://loinc.org", "code": "2947-0", "display": "Sodium"}], "text": "Sodium"}, "subject": {"reference": "urn:uuid:3ed64677-8b2c-440c-a593-aa0e00ac2018"}, "context": {"reference": "urn:uuid:f7de259c-0b6f-402f-a49f-bc8d9c3204f3"}, "effectiveDateTime": "2010-05-25T13:19:17+08:00", "issued": "2010-05-25T13:19:17.553+08:00", "valueQuantity": {"value": 139.38452995881394, "unit": "mmol/L", "system": "http://unitsofmeasure.org", "code": "mmol/L"}}, "request": {"method": "POST", "url": "Observation"}}, {"fullUrl": "urn:uuid:16ecb46c-edea-4317-9bbc-7711e318561e", "resource": {"resourceType": "Observation", "id": "16ecb46c-edea-4317-9bbc-7711e318561e", "meta": {"profile": ["http://standardhealthrecord.org/fhir/StructureDefinition/shr-finding-Observation"]}, "status": "final", "category": [{"coding": [{"system": "http://hl7.org/fhir/observation-category", "code": "laboratory", "display": "laboratory"}]}], "code": {"coding": [{"system": "http://loinc.org", "code": "6298-4", "display": "Potassium"}], "text": "Potassium"}, "subject": {"reference": "urn:uuid:3ed64677-8b2c-440c-a593-aa0e00ac2018"}, "context": {"reference": "urn:uuid:f7de259c-0b6f-402f-a49f-bc8d9c3204f3"}, "effectiveDateTime": "2010-05-25T13:19:17+08:00", "issued": "2010-05-25T13:19:17.553+08:00", "valueQuantity": {"value": 4.0905663290556795, "unit": "mmol/L", "system": "http://unitsofmeasure.org", "code": "mmol/L"}}, "request": {"method": "POST", "url": "Observation"}}, {"fullUrl": "urn:uuid:f2520b08-968b-458e-8c43-8266b91f7819", "resource": {"resourceType": "Observation", "id": "f2520b08-968b-458e-8c43-8266b91f7819", "meta": {"profile": ["http://standardhealthrecord.org/fhir/StructureDefinition/shr-finding-Observation"]}, "status": "final", "category": [{"coding": [{"system": "http://hl7.org/fhir/observation-category", "code": "laboratory", "display": "laboratory"}]}], "code": {"coding": [{"system": "http://loinc.org", "code": "2069-3", "display": "Chloride"}], "text": "Chloride"}, "subject": {"reference": "urn:uuid:3ed64677-8b2c-440c-a593-aa0e00ac2018"}, "context": {"reference": "urn:uuid:f7de259c-0b6f-402f-a49f-bc8d9c3204f3"}, "effectiveDateTime": "2010-05-25T13:19:17+08:00", "issued": "2010-05-25T13:19:17.553+08:00", "valueQuantity": {"value": 110.92456329677525, "unit": "mmol/L", "system": "http://unitsofmeasure.org", "code": "mmol/L"}}, "request": {"method": "POST", "url": "Observation"}}, {"fullUrl": "urn:uuid:24f37241-1227-464c-8e62-38a5d33b2748", "resource": {"resourceType": "Observation", "id": "24f37241-1227-464c-8e62-38a5d33b2748", "meta": {"profile": ["http://standardhealthrecord.org/fhir/StructureDefinition/shr-finding-Observation"]}, "status": "final", "category": [{"coding": [{"system": "http://hl7.org/fhir/observation-category", "code": "laboratory", "display": "laboratory"}]}], "code": {"coding": [{"system": "http://loinc.org", "code": "20565-8", "display": "Carbon Dioxide"}], "text": "Carbon Dioxide"}, "subject": {"reference": "urn:uuid:3ed64677-8b2c-440c-a593-aa0e00ac2018"}, "context": {"reference": "urn:uuid:f7de259c-0b6f-402f-a49f-bc8d9c3204f3"}, "effectiveDateTime": "2010-05-25T13:19:17+08:00", "issued": "2010-05-25T13:19:17.553+08:00", "valueQuantity": {"value": 22.160774173094815, "unit": "mmol/L", "system": "http://unitsofmeasure.org", "code": "mmol/L"}}, "request": {"method": "POST", "url": "Observation"}}, {"fullUrl": "urn:uuid:d60432fc-b247-48d2-a57f-77b0a3a86385", "resource": {"resourceType": "Observation", "id": "d60432fc-b247-48d2-a57f-77b0a3a86385", "meta": {"profile": ["http://standardhealthrecord.org/fhir/StructureDefinition/shr-finding-Observation"]}, "status": "final", "category": [{"coding": [{"system": "http://hl7.org/fhir/observation-category", "code": "survey", "display": "survey"}]}], "code": {"coding": [{"system": "http://loinc.org", "code": "72166-2", "display": "Tobacco smoking status NHIS"}], "text": "Tobacco smoking status NHIS"}, "subject": {"reference": "urn:uuid:3ed64677-8b2c-440c-a593-aa0e00ac2018"}, "context": {"reference": "urn:uuid:f7de259c-0b6f-402f-a49f-bc8d9c3204f3"}, "effectiveDateTime": "2010-05-25T13:19:17+08:00", "issued": "2010-05-25T13:19:17.553+08:00", "valueCodeableConcept": {"coding": [{"system": "http://snomed.info/sct", "code": "266919005", "display": "Never smoker"}], "text": "Never smoker"}}, "request": {"method": "POST", "url": "Observation"}}, {"fullUrl": "urn:uuid:37dcbd01-394f-4fd6-ba07-092637b08813", "resource": {"resourceType": "Observation", "id": "37dcbd01-394f-4fd6-ba07-092637b08813", "meta": {"profile": ["http://standardhealthrecord.org/fhir/StructureDefinition/shr-finding-Observation"]}, "status": "final", "category": [{"coding": [{"system": "http://hl7.org/fhir/observation-category", "code": "laboratory", "display": "laboratory"}]}], "code": {"coding": [{"system": "http://loinc.org", "code": "4548-4", "display": "Hemoglobin A1c/Hemoglobin.total in Blood"}], "text": "Hemoglobin A1c/Hemoglobin.total in Blood"}, "subject": {"reference": "urn:uuid:3ed64677-8b2c-440c-a593-aa0e00ac2018"}, "context": {"reference": "urn:uuid:f7de259c-0b6f-402f-a49f-bc8d9c3204f3"}, "effectiveDateTime": "2010-05-25T13:19:17+08:00", "issued": "2010-05-25T13:19:17.553+08:00", "valueQuantity": {"value": 5.954925024589329, "unit": "%", "system": "http://unitsofmeasure.org", "code": "%"}}, "request": {"method": "POST", "url": "Observation"}}, {"fullUrl": "urn:uuid:0c392cd0-bfcc-43f0-a6a8-d6383c11a717", "resource": {"resourceType": "Immunization", "id": "0c392cd0-bfcc-43f0-a6a8-d6383c11a717", "meta": {"profile": ["http://standardhealthrecord.org/fhir/StructureDefinition/shr-immunization-ImmunizationGiven"]}, "extension": [{"url": "http://standardhealthrecord.org/fhir/StructureDefinition/shr-action-PerformedContext-extension", "extension": [{"url": "http://standardhealthrecord.org/fhir/StructureDefinition/shr-action-Status-extension", "valueCode": "completed"}]}], "status": "completed", "notGiven": false, "vaccineCode": {"coding": [{"system": "http://hl7.org/fhir/sid/cvx", "code": "140", "display": "Influenza, seasonal, injectable, preservative free"}], "text": "Influenza, seasonal, injectable, preservative free"}, "patient": {"reference": "urn:uuid:3ed64677-8b2c-440c-a593-aa0e00ac2018"}, "encounter": {"reference": "urn:uuid:f7de259c-0b6f-402f-a49f-bc8d9c3204f3"}, "date": "2010-05-25T13:19:17+08:00", "primarySource": true}, "request": {"method": "POST", "url": "Immunization"}}, {"fullUrl": "urn:uuid:bc5b9e43-fbc9-4b3b-8189-35f9c341a7e5", "resource": {"resourceType": "DiagnosticReport", "id": "bc5b9e43-fbc9-4b3b-8189-35f9c341a7e5", "status": "final", "code": {"coding": [{"system": "http://loinc.org", "code": "51990-0", "display": "Basic Metabolic Panel"}], "text": "Basic Metabolic Panel"}, "subject": {"reference": "urn:uuid:3ed64677-8b2c-440c-a593-aa0e00ac2018"}, "context": {"reference": "urn:uuid:f7de259c-0b6f-402f-a49f-bc8d9c3204f3"}, "effectiveDateTime": "2010-05-25T13:19:17+08:00", "issued": "2010-05-25T13:19:17.553+08:00", "result": [{"reference": "urn:uuid:54ff1368-c285-40f6-a9f0-da1f83924586", "display": "Glucose"}, {"reference": "urn:uuid:5382ed08-bd70-4a45-ab80-db125802f2ce", "display": "Urea Nitrogen"}, {"reference": "urn:uuid:4bb09f51-2dd0-4903-8d43-f430cf6d8f7f", "display": "Creatinine"}, {"reference": "urn:uuid:6f03c7aa-caf4-4cd7-af65-6b6ddf31beb5", "display": "Calcium"}, {"reference": "urn:uuid:84ddc0dd-5394-4da2-a54e-e8a620b8d464", "display": "Sodium"}, {"reference": "urn:uuid:16ecb46c-edea-4317-9bbc-7711e318561e", "display": "Potassium"}, {"reference": "urn:uuid:f2520b08-968b-458e-8c43-8266b91f7819", "display": "Chloride"}, {"reference": "urn:uuid:24f37241-1227-464c-8e62-38a5d33b2748", "display": "Carbon Dioxide"}]}, "request": {"method": "POST", "url": "DiagnosticReport"}}, {"fullUrl": "urn:uuid:1e7184f5-ca12-4a9c-ad43-a1c4597cbff8", "resource": {"resourceType": "Claim", "id": "1e7184f5-ca12-4a9c-ad43-a1c4597cbff8", "status": "active", "use": "complete", "patient": {"reference": "urn:uuid:3ed64677-8b2c-440c-a593-aa0e00ac2018"}, "billablePeriod": {"start": "2010-05-25T13:19:17+08:00", "end": "2010-05-25T13:34:17+08:00"}, "organization": {"reference": "urn:uuid:609c86d7-5324-477b-99a2-b1608551ef1f"}, "information": [{"sequence": 1, "category": {"coding": [{"system": "http://hl7.org/fhir/claiminformationcategory", "code": "info"}]}, "valueReference": {"reference": "urn:uuid:0c392cd0-bfcc-43f0-a6a8-d6383c11a717"}}], "item": [{"sequence": 1, "encounter": [{"reference": "urn:uuid:f7de259c-0b6f-402f-a49f-bc8d9c3204f3"}]}, {"sequence": 2, "informationLinkId": [1], "net": {"value": 140.52, "system": "urn:iso:std:iso:4217", "code": "USD"}}], "total": {"value": 265.52, "system": "urn:iso:std:iso:4217", "code": "USD"}}, "request": {"method": "POST", "url": "Claim"}}, {"fullUrl": "urn:uuid:e377f577-5183-4d18-805b-2d3a36e64f01", "resource": {"resourceType": "Encounter", "id": "e377f577-5183-4d18-805b-2d3a36e64f01", "meta": {"profile": ["http://standardhealthrecord.org/fhir/StructureDefinition/shr-encounter-EncounterPerformed"]}, "extension": [{"url": "http://standardhealthrecord.org/fhir/StructureDefinition/shr-action-PerformedContext-extension", "extension": [{"url": "http://standardhealthrecord.org/fhir/StructureDefinition/shr-action-Status-extension", "valueCode": "finished"}]}], "status": "finished", "class": {"code": "WELLNESS"}, "type": [{"coding": [{"system": "http://snomed.info/sct", "code": "185349003", "display": "Encounter for check up (procedure)"}], "text": "Encounter for check up (procedure)"}], "subject": {"reference": "urn:uuid:3ed64677-8b2c-440c-a593-aa0e00ac2018"}, "period": {"start": "2013-05-28T13:19:17+08:00", "end": "2013-05-28T13:49:17+08:00"}, "serviceProvider": {"reference": "urn:uuid:609c86d7-5324-477b-99a2-b1608551ef1f"}}, "request": {"method": "POST", "url": "Encounter"}}, {"fullUrl": "urn:uuid:e5fbe278-d1b3-4496-9794-daa7ab152ddd", "resource": {"resourceType": "Observation", "id": "e5fbe278-d1b3-4496-9794-daa7ab152ddd", "meta": {"profile": ["http://standardhealthrecord.org/fhir/StructureDefinition/shr-finding-Observation", "http://standardhealthrecord.org/fhir/StructureDefinition/shr-vital-VitalSign", "http://standardhealthrecord.org/fhir/StructureDefinition/shr-vital-BodyHeight"]}, "status": "final", "category": [{"coding": [{"system": "http://hl7.org/fhir/observation-category", "code": "vital-signs", "display": "vital-signs"}]}], "code": {"coding": [{"system": "http://loinc.org", "code": "8302-2", "display": "Body Height"}], "text": "Body Height"}, "subject": {"reference": "urn:uuid:3ed64677-8b2c-440c-a593-aa0e00ac2018"}, "context": {"reference": "urn:uuid:e377f577-5183-4d18-805b-2d3a36e64f01"}, "effectiveDateTime": "2013-05-28T13:19:17+08:00", "issued": "2013-05-28T13:19:17.553+08:00", "valueQuantity": {"value": 173.5779130511357, "unit": "cm", "system": "http://unitsofmeasure.org", "code": "cm"}}, "request": {"method": "POST", "url": "Observation"}}, {"fullUrl": "urn:uuid:5f6dc472-1a4a-4827-91a2-a97725dfa797", "resource": {"resourceType": "Observation", "id": "5f6dc472-1a4a-4827-91a2-a97725dfa797", "meta": {"profile": ["http://standardhealthrecord.org/fhir/StructureDefinition/shr-finding-Observation", "http://standardhealthrecord.org/fhir/StructureDefinition/shr-vital-VitalSign", "http://standardhealthrecord.org/fhir/StructureDefinition/shr-vital-BodyWeight"]}, "status": "final", "category": [{"coding": [{"system": "http://hl7.org/fhir/observation-category", "code": "vital-signs", "display": "vital-signs"}]}], "code": {"coding": [{"system": "http://loinc.org", "code": "29463-7", "display": "Body Weight"}], "text": "Body Weight"}, "subject": {"reference": "urn:uuid:3ed64677-8b2c-440c-a593-aa0e00ac2018"}, "context": {"reference": "urn:uuid:e377f577-5183-4d18-805b-2d3a36e64f01"}, "effectiveDateTime": "2013-05-28T13:19:17+08:00", "issued": "2013-05-28T13:19:17.553+08:00", "valueQuantity": {"value": 88.0651495610623, "unit": "kg", "system": "http://unitsofmeasure.org", "code": "kg"}}, "request": {"method": "POST", "url": "Observation"}}, {"fullUrl": "urn:uuid:0724e1f5-a750-4578-bf69-42a4e15a3133", "resource": {"resourceType": "Observation", "id": "0724e1f5-a750-4578-bf69-42a4e15a3133", "meta": {"profile": ["http://standardhealthrecord.org/fhir/StructureDefinition/shr-finding-Observation", "http://standardhealthrecord.org/fhir/StructureDefinition/shr-vital-VitalSign", "http://standardhealthrecord.org/fhir/StructureDefinition/shr-vital-BodyMassIndex"]}, "status": "final", "category": [{"coding": [{"system": "http://hl7.org/fhir/observation-category", "code": "vital-signs", "display": "vital-signs"}]}], "code": {"coding": [{"system": "http://loinc.org", "code": "39156-5", "display": "Body Mass Index"}], "text": "Body Mass Index"}, "subject": {"reference": "urn:uuid:3ed64677-8b2c-440c-a593-aa0e00ac2018"}, "context": {"reference": "urn:uuid:e377f577-5183-4d18-805b-2d3a36e64f01"}, "effectiveDateTime": "2013-05-28T13:19:17+08:00", "issued": "2013-05-28T13:19:17.553+08:00", "valueQuantity": {"value": 29.229080409764556, "unit": "kg/m2", "system": "http://unitsofmeasure.org", "code": "kg/m2"}}, "request": {"method": "POST", "url": "Observation"}}, {"fullUrl": "urn:uuid:d97ef0b5-c119-4807-823d-93741d8cd1b5", "resource": {"resourceType": "Observation", "id": "d97ef0b5-c119-4807-823d-93741d8cd1b5", "meta": {"profile": ["http://standardhealthrecord.org/fhir/StructureDefinition/shr-finding-Observation", "http://standardhealthrecord.org/fhir/StructureDefinition/shr-vital-VitalSign", "http://standardhealthrecord.org/fhir/StructureDefinition/shr-vital-BloodPressure"]}, "status": "final", "category": [{"coding": [{"system": "http://hl7.org/fhir/observation-category", "code": "vital-signs", "display": "vital-signs"}]}], "code": {"coding": [{"system": "http://loinc.org", "code": "55284-4", "display": "Blood Pressure"}], "text": "Blood Pressure"}, "subject": {"reference": "urn:uuid:3ed64677-8b2c-440c-a593-aa0e00ac2018"}, "context": {"reference": "urn:uuid:e377f577-5183-4d18-805b-2d3a36e64f01"}, "effectiveDateTime": "2013-05-28T13:19:17+08:00", "issued": "2013-05-28T13:19:17.553+08:00", "component": [{"code": {"coding": [{"system": "http://loinc.org", "code": "8462-4", "display": "Diastolic Blood Pressure"}], "text": "Diastolic Blood Pressure"}, "valueQuantity": {"value": 88.42201001324456, "unit": "mmHg", "system": "http://unitsofmeasure.org", "code": "mmHg"}}, {"code": {"coding": [{"system": "http://loinc.org", "code": "8480-6", "display": "Systolic Blood Pressure"}], "text": "Systolic Blood Pressure"}, "valueQuantity": {"value": 115.20242614818186, "unit": "mmHg", "system": "http://unitsofmeasure.org", "code": "mmHg"}}]}, "request": {"method": "POST", "url": "Observation"}}, {"fullUrl": "urn:uuid:4c681deb-e0d1-43dd-a103-47af0b78566d", "resource": {"resourceType": "Observation", "id": "4c681deb-e0d1-43dd-a103-47af0b78566d", "meta": {"profile": ["http://standardhealthrecord.org/fhir/StructureDefinition/shr-finding-Observation"]}, "status": "final", "category": [{"coding": [{"system": "http://hl7.org/fhir/observation-category", "code": "laboratory", "display": "laboratory"}]}], "code": {"coding": [{"system": "http://loinc.org", "code": "2339-0", "display": "Glucose"}], "text": "Glucose"}, "subject": {"reference": "urn:uuid:3ed64677-8b2c-440c-a593-aa0e00ac2018"}, "context": {"reference": "urn:uuid:e377f577-5183-4d18-805b-2d3a36e64f01"}, "effectiveDateTime": "2013-05-28T13:19:17+08:00", "issued": "2013-05-28T13:19:17.553+08:00", "valueQuantity": {"value": 65.9596171479621, "unit": "mg/dL", "system": "http://unitsofmeasure.org", "code": "mg/dL"}}, "request": {"method": "POST", "url": "Observation"}}, {"fullUrl": "urn:uuid:ace46d3b-f9b2-413d-8348-2276aaf740b4", "resource": {"resourceType": "Observation", "id": "ace46d3b-f9b2-413d-8348-2276aaf740b4", "meta": {"profile": ["http://standardhealthrecord.org/fhir/StructureDefinition/shr-finding-Observation"]}, "status": "final", "category": [{"coding": [{"system": "http://hl7.org/fhir/observation-category", "code": "laboratory", "display": "laboratory"}]}], "code": {"coding": [{"system": "http://loinc.org", "code": "6299-2", "display": "Urea Nitrogen"}], "text": "Urea Nitrogen"}, "subject": {"reference": "urn:uuid:3ed64677-8b2c-440c-a593-aa0e00ac2018"}, "context": {"reference": "urn:uuid:e377f577-5183-4d18-805b-2d3a36e64f01"}, "effectiveDateTime": "2013-05-28T13:19:17+08:00", "issued": "2013-05-28T13:19:17.553+08:00", "valueQuantity": {"value": 14.991859639535159, "unit": "mg/dL", "system": "http://unitsofmeasure.org", "code": "mg/dL"}}, "request": {"method": "POST", "url": "Observation"}}, {"fullUrl": "urn:uuid:a8be82ad-9f4a-436d-9087-7e1f711192d7", "resource": {"resourceType": "Observation", "id": "a8be82ad-9f4a-436d-9087-7e1f711192d7", "meta": {"profile": ["http://standardhealthrecord.org/fhir/StructureDefinition/shr-finding-Observation"]}, "status": "final", "category": [{"coding": [{"system": "http://hl7.org/fhir/observation-category", "code": "laboratory", "display": "laboratory"}]}], "code": {"coding": [{"system": "http://loinc.org", "code": "38483-4", "display": "Creatinine"}], "text": "Creatinine"}, "subject": {"reference": "urn:uuid:3ed64677-8b2c-440c-a593-aa0e00ac2018"}, "context": {"reference": "urn:uuid:e377f577-5183-4d18-805b-2d3a36e64f01"}, "effectiveDateTime": "2013-05-28T13:19:17+08:00", "issued": "2013-05-28T13:19:17.553+08:00", "valueQuantity": {"value": 1.333208514188304, "unit": "mg/dL", "system": "http://unitsofmeasure.org", "code": "mg/dL"}}, "request": {"method": "POST", "url": "Observation"}}, {"fullUrl": "urn:uuid:86e64f67-d5d7-413e-bb15-c06ee161e1e3", "resource": {"resourceType": "Observation", "id": "86e64f67-d5d7-413e-bb15-c06ee161e1e3", "meta": {"profile": ["http://standardhealthrecord.org/fhir/StructureDefinition/shr-finding-Observation"]}, "status": "final", "category": [{"coding": [{"system": "http://hl7.org/fhir/observation-category", "code": "laboratory", "display": "laboratory"}]}], "code": {"coding": [{"system": "http://loinc.org", "code": "49765-1", "display": "Calcium"}], "text": "Calcium"}, "subject": {"reference": "urn:uuid:3ed64677-8b2c-440c-a593-aa0e00ac2018"}, "context": {"reference": "urn:uuid:e377f577-5183-4d18-805b-2d3a36e64f01"}, "effectiveDateTime": "2013-05-28T13:19:17+08:00", "issued": "2013-05-28T13:19:17.553+08:00", "valueQuantity": {"value": 9.258395612049297, "unit": "mg/dL", "system": "http://unitsofmeasure.org", "code": "mg/dL"}}, "request": {"method": "POST", "url": "Observation"}}, {"fullUrl": "urn:uuid:64b42964-7ff1-4940-933d-fe2a4c7f7143", "resource": {"resourceType": "Observation", "id": "64b42964-7ff1-4940-933d-fe2a4c7f7143", "meta": {"profile": ["http://standardhealthrecord.org/fhir/StructureDefinition/shr-finding-Observation"]}, "status": "final", "category": [{"coding": [{"system": "http://hl7.org/fhir/observation-category", "code": "laboratory", "display": "laboratory"}]}], "code": {"coding": [{"system": "http://loinc.org", "code": "2947-0", "display": "Sodium"}], "text": "Sodium"}, "subject": {"reference": "urn:uuid:3ed64677-8b2c-440c-a593-aa0e00ac2018"}, "context": {"reference": "urn:uuid:e377f577-5183-4d18-805b-2d3a36e64f01"}, "effectiveDateTime": "2013-05-28T13:19:17+08:00", "issued": "2013-05-28T13:19:17.553+08:00", "valueQuantity": {"value": 136.3998350349296, "unit": "mmol/L", "system": "http://unitsofmeasure.org", "code": "mmol/L"}}, "request": {"method": "POST", "url": "Observation"}}, {"fullUrl": "urn:uuid:48d82495-bf56-463b-bbaf-9ad95583f80c", "resource": {"resourceType": "Observation", "id": "48d82495-bf56-463b-bbaf-9ad95583f80c", "meta": {"profile": ["http://standardhealthrecord.org/fhir/StructureDefinition/shr-finding-Observation"]}, "status": "final", "category": [{"coding": [{"system": "http://hl7.org/fhir/observation-category", "code": "laboratory", "display": "laboratory"}]}], "code": {"coding": [{"system": "http://loinc.org", "code": "6298-4", "display": "Potassium"}], "text": "Potassium"}, "subject": {"reference": "urn:uuid:3ed64677-8b2c-440c-a593-aa0e00ac2018"}, "context": {"reference": "urn:uuid:e377f577-5183-4d18-805b-2d3a36e64f01"}, "effectiveDateTime": "2013-05-28T13:19:17+08:00", "issued": "2013-05-28T13:19:17.553+08:00", "valueQuantity": {"value": 4.800950265595575, "unit": "mmol/L", "system": "http://unitsofmeasure.org", "code": "mmol/L"}}, "request": {"method": "POST", "url": "Observation"}}, {"fullUrl": "urn:uuid:06cc65a3-0c26-47b6-bbb3-7085c53f920c", "resource": {"resourceType": "Observation", "id": "06cc65a3-0c26-47b6-bbb3-7085c53f920c", "meta": {"profile": ["http://standardhealthrecord.org/fhir/StructureDefinition/shr-finding-Observation"]}, "status": "final", "category": [{"coding": [{"system": "http://hl7.org/fhir/observation-category", "code": "laboratory", "display": "laboratory"}]}], "code": {"coding": [{"system": "http://loinc.org", "code": "2069-3", "display": "Chloride"}], "text": "Chloride"}, "subject": {"reference": "urn:uuid:3ed64677-8b2c-440c-a593-aa0e00ac2018"}, "context": {"reference": "urn:uuid:e377f577-5183-4d18-805b-2d3a36e64f01"}, "effectiveDateTime": "2013-05-28T13:19:17+08:00", "issued": "2013-05-28T13:19:17.553+08:00", "valueQuantity": {"value": 108.19955465342672, "unit": "mmol/L", "system": "http://unitsofmeasure.org", "code": "mmol/L"}}, "request": {"method": "POST", "url": "Observation"}}, {"fullUrl": "urn:uuid:699544a9-7ede-406b-9f84-392231a4ef08", "resource": {"resourceType": "Observation", "id": "699544a9-7ede-406b-9f84-392231a4ef08", "meta": {"profile": ["http://standardhealthrecord.org/fhir/StructureDefinition/shr-finding-Observation"]}, "status": "final", "category": [{"coding": [{"system": "http://hl7.org/fhir/observation-category", "code": "laboratory", "display": "laboratory"}]}], "code": {"coding": [{"system": "http://loinc.org", "code": "20565-8", "display": "Carbon Dioxide"}], "text": "Carbon Dioxide"}, "subject": {"reference": "urn:uuid:3ed64677-8b2c-440c-a593-aa0e00ac2018"}, "context": {"reference": "urn:uuid:e377f577-5183-4d18-805b-2d3a36e64f01"}, "effectiveDateTime": "2013-05-28T13:19:17+08:00", "issued": "2013-05-28T13:19:17.553+08:00", "valueQuantity": {"value": 25.7539587370266, "unit": "mmol/L", "system": "http://unitsofmeasure.org", "code": "mmol/L"}}, "request": {"method": "POST", "url": "Observation"}}, {"fullUrl": "urn:uuid:7d0bd7d3-22c3-4065-913f-3814cce590eb", "resource": {"resourceType": "Observation", "id": "7d0bd7d3-22c3-4065-913f-3814cce590eb", "meta": {"profile": ["http://standardhealthrecord.org/fhir/StructureDefinition/shr-finding-Observation"]}, "status": "final", "category": [{"coding": [{"system": "http://hl7.org/fhir/observation-category", "code": "laboratory", "display": "laboratory"}]}], "code": {"coding": [{"system": "http://loinc.org", "code": "2093-3", "display": "Total Cholesterol"}], "text": "Total Cholesterol"}, "subject": {"reference": "urn:uuid:3ed64677-8b2c-440c-a593-aa0e00ac2018"}, "context": {"reference": "urn:uuid:e377f577-5183-4d18-805b-2d3a36e64f01"}, "effectiveDateTime": "2013-05-28T13:19:17+08:00", "issued": "2013-05-28T13:19:17.553+08:00", "valueQuantity": {"value": 165.7201501733888, "unit": "mg/dL", "system": "http://unitsofmeasure.org", "code": "mg/dL"}}, "request": {"method": "POST", "url": "Observation"}}, {"fullUrl": "urn:uuid:bd397024-6d5d-4868-8d3c-393062376bcb", "resource": {"resourceType": "Observation", "id": "bd397024-6d5d-4868-8d3c-393062376bcb", "meta": {"profile": ["http://standardhealthrecord.org/fhir/StructureDefinition/shr-finding-Observation"]}, "status": "final", "category": [{"coding": [{"system": "http://hl7.org/fhir/observation-category", "code": "laboratory", "display": "laboratory"}]}], "code": {"coding": [{"system": "http://loinc.org", "code": "2571-8", "display": "Triglycerides"}], "text": "Triglycerides"}, "subject": {"reference": "urn:uuid:3ed64677-8b2c-440c-a593-aa0e00ac2018"}, "context": {"reference": "urn:uuid:e377f577-5183-4d18-805b-2d3a36e64f01"}, "effectiveDateTime": "2013-05-28T13:19:17+08:00", "issued": "2013-05-28T13:19:17.553+08:00", "valueQuantity": {"value": 128.21078312238194, "unit": "mg/dL", "system": "http://unitsofmeasure.org", "code": "mg/dL"}}, "request": {"method": "POST", "url": "Observation"}}, {"fullUrl": "urn:uuid:0ecbd06d-bdd5-458a-88e5-461d8e81a1d4", "resource": {"resourceType": "Observation", "id": "0ecbd06d-bdd5-458a-88e5-461d8e81a1d4", "meta": {"profile": ["http://standardhealthrecord.org/fhir/StructureDefinition/shr-finding-Observation"]}, "status": "final", "category": [{"coding": [{"system": "http://hl7.org/fhir/observation-category", "code": "laboratory", "display": "laboratory"}]}], "code": {"coding": [{"system": "http://loinc.org", "code": "18262-6", "display": "Low Density Lipoprotein Cholesterol"}], "text": "Low Density Lipoprotein Cholesterol"}, "subject": {"reference": "urn:uuid:3ed64677-8b2c-440c-a593-aa0e00ac2018"}, "context": {"reference": "urn:uuid:e377f577-5183-4d18-805b-2d3a36e64f01"}, "effectiveDateTime": "2013-05-28T13:19:17+08:00", "issued": "2013-05-28T13:19:17.553+08:00", "valueQuantity": {"value": 77.76868832800302, "unit": "mg/dL", "system": "http://unitsofmeasure.org", "code": "mg/dL"}}, "request": {"method": "POST", "url": "Observation"}}, {"fullUrl": "urn:uuid:afa954d5-526e-4bf1-af86-62f498555178", "resource": {"resourceType": "Observation", "id": "afa954d5-526e-4bf1-af86-62f498555178", "meta": {"profile": ["http://standardhealthrecord.org/fhir/StructureDefinition/shr-finding-Observation"]}, "status": "final", "category": [{"coding": [{"system": "http://hl7.org/fhir/observation-category", "code": "laboratory", "display": "laboratory"}]}], "code": {"coding": [{"system": "http://loinc.org", "code": "2085-9", "display": "High Density Lipoprotein Cholesterol"}], "text": "High Density Lipoprotein Cholesterol"}, "subject": {"reference": "urn:uuid:3ed64677-8b2c-440c-a593-aa0e00ac2018"}, "context": {"reference": "urn:uuid:e377f577-5183-4d18-805b-2d3a36e64f01"}, "effectiveDateTime": "2013-05-28T13:19:17+08:00", "issued": "2013-05-28T13:19:17.553+08:00", "valueQuantity": {"value": 62.30930522090937, "unit": "mg/dL", "system": "http://unitsofmeasure.org", "code": "mg/dL"}}, "request": {"method": "POST", "url": "Observation"}}, {"fullUrl": "urn:uuid:31445285-6555-4733-a4ad-d2e7eef7d779", "resource": {"resourceType": "Observation", "id": "31445285-6555-4733-a4ad-d2e7eef7d779", "meta": {"profile": ["http://standardhealthrecord.org/fhir/StructureDefinition/shr-finding-Observation"]}, "status": "final", "category": [{"coding": [{"system": "http://hl7.org/fhir/observation-category", "code": "survey", "display": "survey"}]}], "code": {"coding": [{"system": "http://loinc.org", "code": "72166-2", "display": "Tobacco smoking status NHIS"}], "text": "Tobacco smoking status NHIS"}, "subject": {"reference": "urn:uuid:3ed64677-8b2c-440c-a593-aa0e00ac2018"}, "context": {"reference": "urn:uuid:e377f577-5183-4d18-805b-2d3a36e64f01"}, "effectiveDateTime": "2013-05-28T13:19:17+08:00", "issued": "2013-05-28T13:19:17.553+08:00", "valueCodeableConcept": {"coding": [{"system": "http://snomed.info/sct", "code": "266919005", "display": "Never smoker"}], "text": "Never smoker"}}, "request": {"method": "POST", "url": "Observation"}}, {"fullUrl": "urn:uuid:9ceb5e41-9356-4981-93b4-224242889211", "resource": {"resourceType": "Observation", "id": "9ceb5e41-9356-4981-93b4-224242889211", "meta": {"profile": ["http://standardhealthrecord.org/fhir/StructureDefinition/shr-finding-Observation"]}, "status": "final", "category": [{"coding": [{"system": "http://hl7.org/fhir/observation-category", "code": "laboratory", "display": "laboratory"}]}], "code": {"coding": [{"system": "http://loinc.org", "code": "4548-4", "display": "Hemoglobin A1c/Hemoglobin.total in Blood"}], "text": "Hemoglobin A1c/Hemoglobin.total in Blood"}, "subject": {"reference": "urn:uuid:3ed64677-8b2c-440c-a593-aa0e00ac2018"}, "context": {"reference": "urn:uuid:e377f577-5183-4d18-805b-2d3a36e64f01"}, "effectiveDateTime": "2013-05-28T13:19:17+08:00", "issued": "2013-05-28T13:19:17.553+08:00", "valueQuantity": {"value": 6.1113527447454326, "unit": "%", "system": "http://unitsofmeasure.org", "code": "%"}}, "request": {"method": "POST", "url": "Observation"}}, {"fullUrl": "urn:uuid:ffd786dd-6105-4e19-aad5-1bd0e862f06d", "resource": {"resourceType": "Procedure", "id": "ffd786dd-6105-4e19-aad5-1bd0e862f06d", "meta": {"profile": ["http://standardhealthrecord.org/fhir/StructureDefinition/shr-procedure-ProcedurePerformed"]}, "extension": [{"url": "http://standardhealthrecord.org/fhir/StructureDefinition/shr-action-PerformedContext-extension", "extension": [{"url": "http://standardhealthrecord.org/fhir/StructureDefinition/shr-action-Status-extension", "valueCode": "completed"}]}], "status": "completed", "code": {"coding": [{"system": "http://snomed.info/sct", "code": "428191000124101", "display": "Documentation of current medications"}], "text": "Documentation of current medications"}, "subject": {"reference": "urn:uuid:3ed64677-8b2c-440c-a593-aa0e00ac2018"}, "context": {"reference": "urn:uuid:e377f577-5183-4d18-805b-2d3a36e64f01"}, "performedPeriod": {"start": "2013-05-28T13:19:17+08:00", "end": "2013-05-28T13:34:17+08:00"}}, "request": {"method": "POST", "url": "Procedure"}}, {"fullUrl": "urn:uuid:3b08d6cc-6507-4a1e-9c45-c7bf9324f9c9", "resource": {"resourceType": "Immunization", "id": "3b08d6cc-6507-4a1e-9c45-c7bf9324f9c9", "meta": {"profile": ["http://standardhealthrecord.org/fhir/StructureDefinition/shr-immunization-ImmunizationGiven"]}, "extension": [{"url": "http://standardhealthrecord.org/fhir/StructureDefinition/shr-action-PerformedContext-extension", "extension": [{"url": "http://standardhealthrecord.org/fhir/StructureDefinition/shr-action-Status-extension", "valueCode": "completed"}]}], "status": "completed", "notGiven": false, "vaccineCode": {"coding": [{"system": "http://hl7.org/fhir/sid/cvx", "code": "140", "display": "Influenza, seasonal, injectable, preservative free"}], "text": "Influenza, seasonal, injectable, preservative free"}, "patient": {"reference": "urn:uuid:3ed64677-8b2c-440c-a593-aa0e00ac2018"}, "encounter": {"reference": "urn:uuid:e377f577-5183-4d18-805b-2d3a36e64f01"}, "date": "2013-05-28T13:19:17+08:00", "primarySource": true}, "request": {"method": "POST", "url": "Immunization"}}, {"fullUrl": "urn:uuid:0a062c2f-6288-4bc0-8576-a980110ccbc6", "resource": {"resourceType": "Immunization", "id": "0a062c2f-6288-4bc0-8576-a980110ccbc6", "meta": {"profile": ["http://standardhealthrecord.org/fhir/StructureDefinition/shr-immunization-ImmunizationGiven"]}, "extension": [{"url": "http://standardhealthrecord.org/fhir/StructureDefinition/shr-action-PerformedContext-extension", "extension": [{"url": "http://standardhealthrecord.org/fhir/StructureDefinition/shr-action-Status-extension", "valueCode": "completed"}]}], "status": "completed", "notGiven": false, "vaccineCode": {"coding": [{"system": "http://hl7.org/fhir/sid/cvx", "code": "113", "display": "Td (adult) preservative free"}], "text": "Td (adult) preservative free"}, "patient": {"reference": "urn:uuid:3ed64677-8b2c-440c-a593-aa0e00ac2018"}, "encounter": {"reference": "urn:uuid:e377f577-5183-4d18-805b-2d3a36e64f01"}, "date": "2013-05-28T13:19:17+08:00", "primarySource": true}, "request": {"method": "POST", "url": "Immunization"}}, {"fullUrl": "urn:uuid:ae2bffbf-bb19-4e70-a9f0-15d909c6ca98", "resource": {"resourceType": "DiagnosticReport", "id": "ae2bffbf-bb19-4e70-a9f0-15d909c6ca98", "status": "final", "code": {"coding": [{"system": "http://loinc.org", "code": "51990-0", "display": "Basic Metabolic Panel"}], "text": "Basic Metabolic Panel"}, "subject": {"reference": "urn:uuid:3ed64677-8b2c-440c-a593-aa0e00ac2018"}, "context": {"reference": "urn:uuid:e377f577-5183-4d18-805b-2d3a36e64f01"}, "effectiveDateTime": "2013-05-28T13:19:17+08:00", "issued": "2013-05-28T13:19:17.553+08:00", "result": [{"reference": "urn:uuid:4c681deb-e0d1-43dd-a103-47af0b78566d", "display": "Glucose"}, {"reference": "urn:uuid:ace46d3b-f9b2-413d-8348-2276aaf740b4", "display": "Urea Nitrogen"}, {"reference": "urn:uuid:a8be82ad-9f4a-436d-9087-7e1f711192d7", "display": "Creatinine"}, {"reference": "urn:uuid:86e64f67-d5d7-413e-bb15-c06ee161e1e3", "display": "Calcium"}, {"reference": "urn:uuid:64b42964-7ff1-4940-933d-fe2a4c7f7143", "display": "Sodium"}, {"reference": "urn:uuid:48d82495-bf56-463b-bbaf-9ad95583f80c", "display": "Potassium"}, {"reference": "urn:uuid:06cc65a3-0c26-47b6-bbb3-7085c53f920c", "display": "Chloride"}, {"reference": "urn:uuid:699544a9-7ede-406b-9f84-392231a4ef08", "display": "Carbon Dioxide"}]}, "request": {"method": "POST", "url": "DiagnosticReport"}}, {"fullUrl": "urn:uuid:63b204fb-8e01-4356-a28e-33edf38b99a2", "resource": {"resourceType": "DiagnosticReport", "id": "63b204fb-8e01-4356-a28e-33edf38b99a2", "status": "final", "code": {"coding": [{"system": "http://loinc.org", "code": "57698-3", "display": "Lipid Panel"}], "text": "Lipid Panel"}, "subject": {"reference": "urn:uuid:3ed64677-8b2c-440c-a593-aa0e00ac2018"}, "context": {"reference": "urn:uuid:e377f577-5183-4d18-805b-2d3a36e64f01"}, "effectiveDateTime": "2013-05-28T13:19:17+08:00", "issued": "2013-05-28T13:19:17.553+08:00", "result": [{"reference": "urn:uuid:7d0bd7d3-22c3-4065-913f-3814cce590eb", "display": "Total Cholesterol"}, {"reference": "urn:uuid:bd397024-6d5d-4868-8d3c-393062376bcb", "display": "Triglycerides"}, {"reference": "urn:uuid:0ecbd06d-bdd5-458a-88e5-461d8e81a1d4", "display": "Low Density Lipoprotein Cholesterol"}, {"reference": "urn:uuid:afa954d5-526e-4bf1-af86-62f498555178", "display": "High Density Lipoprotein Cholesterol"}]}, "request": {"method": "POST", "url": "DiagnosticReport"}}, {"fullUrl": "urn:uuid:503e6bd9-bf12-4589-95d0-be51a5070f66", "resource": {"resourceType": "Claim", "id": "503e6bd9-bf12-4589-95d0-be51a5070f66", "status": "active", "use": "complete", "patient": {"reference": "urn:uuid:3ed64677-8b2c-440c-a593-aa0e00ac2018"}, "billablePeriod": {"start": "2013-05-28T13:19:17+08:00", "end": "2013-05-28T13:49:17+08:00"}, "organization": {"reference": "urn:uuid:609c86d7-5324-477b-99a2-b1608551ef1f"}, "information": [{"sequence": 1, "category": {"coding": [{"system": "http://hl7.org/fhir/claiminformationcategory", "code": "info"}]}, "valueReference": {"reference": "urn:uuid:3b08d6cc-6507-4a1e-9c45-c7bf9324f9c9"}}, {"sequence": 2, "category": {"coding": [{"system": "http://hl7.org/fhir/claiminformationcategory", "code": "info"}]}, "valueReference": {"reference": "urn:uuid:0a062c2f-6288-4bc0-8576-a980110ccbc6"}}], "procedure": [{"sequence": 1, "procedureReference": {"reference": "urn:uuid:ffd786dd-6105-4e19-aad5-1bd0e862f06d"}}], "item": [{"sequence": 1, "encounter": [{"reference": "urn:uuid:e377f577-5183-4d18-805b-2d3a36e64f01"}]}, {"sequence": 2, "informationLinkId": [1], "net": {"value": 140.52, "system": "urn:iso:std:iso:4217", "code": "USD"}}, {"sequence": 3, "informationLinkId": [2], "net": {"value": 140.52, "system": "urn:iso:std:iso:4217", "code": "USD"}}, {"sequence": 4, "procedureLinkId": [1], "net": {"value": 563.19, "system": "urn:iso:std:iso:4217", "code": "USD"}}], "total": {"value": 969.23, "system": "urn:iso:std:iso:4217", "code": "USD"}}, "request": {"method": "POST", "url": "Claim"}}, {"fullUrl": "urn:uuid:cc8158c0-c184-451b-8d1d-56ae0b98254c", "resource": {"resourceType": "Encounter", "id": "cc8158c0-c184-451b-8d1d-56ae0b98254c", "meta": {"profile": ["http://standardhealthrecord.org/fhir/StructureDefinition/shr-encounter-EncounterPerformed"]}, "extension": [{"url": "http://standardhealthrecord.org/fhir/StructureDefinition/shr-action-PerformedContext-extension", "extension": [{"url": "http://standardhealthrecord.org/fhir/StructureDefinition/shr-action-Status-extension", "valueCode": "finished"}]}], "status": "finished", "class": {"code": "WELLNESS"}, "type": [{"coding": [{"system": "http://snomed.info/sct", "code": "185349003", "display": "Encounter for check up (procedure)"}], "text": "Encounter for check up (procedure)"}], "subject": {"reference": "urn:uuid:3ed64677-8b2c-440c-a593-aa0e00ac2018"}, "period": {"start": "2016-05-31T12:19:17+07:00", "end": "2016-05-31T12:34:17+07:00"}, "serviceProvider": {"reference": "urn:uuid:609c86d7-5324-477b-99a2-b1608551ef1f"}}, "request": {"method": "POST", "url": "Encounter"}}, {"fullUrl": "urn:uuid:4dfb737f-de1b-4613-a37a-3219319bd9ea", "resource": {"resourceType": "Observation", "id": "4dfb737f-de1b-4613-a37a-3219319bd9ea", "meta": {"profile": ["http://standardhealthrecord.org/fhir/StructureDefinition/shr-finding-Observation", "http://standardhealthrecord.org/fhir/StructureDefinition/shr-vital-VitalSign", "http://standardhealthrecord.org/fhir/StructureDefinition/shr-vital-BodyHeight"]}, "status": "final", "category": [{"coding": [{"system": "http://hl7.org/fhir/observation-category", "code": "vital-signs", "display": "vital-signs"}]}], "code": {"coding": [{"system": "http://loinc.org", "code": "8302-2", "display": "Body Height"}], "text": "Body Height"}, "subject": {"reference": "urn:uuid:3ed64677-8b2c-440c-a593-aa0e00ac2018"}, "context": {"reference": "urn:uuid:cc8158c0-c184-451b-8d1d-56ae0b98254c"}, "effectiveDateTime": "2016-05-31T12:19:17+07:00", "issued": "2016-05-31T12:19:17.553+07:00", "valueQuantity": {"value": 173.5779130511357, "unit": "cm", "system": "http://unitsofmeasure.org", "code": "cm"}}, "request": {"method": "POST", "url": "Observation"}}, {"fullUrl": "urn:uuid:86983700-72b7-41d8-b114-729b949c5b58", "resource": {"resourceType": "Observation", "id": "86983700-72b7-41d8-b114-729b949c5b58", "meta": {"profile": ["http://standardhealthrecord.org/fhir/StructureDefinition/shr-finding-Observation", "http://standardhealthrecord.org/fhir/StructureDefinition/shr-vital-VitalSign", "http://standardhealthrecord.org/fhir/StructureDefinition/shr-vital-BodyWeight"]}, "status": "final", "category": [{"coding": [{"system": "http://hl7.org/fhir/observation-category", "code": "vital-signs", "display": "vital-signs"}]}], "code": {"coding": [{"system": "http://loinc.org", "code": "29463-7", "display": "Body Weight"}], "text": "Body Weight"}, "subject": {"reference": "urn:uuid:3ed64677-8b2c-440c-a593-aa0e00ac2018"}, "context": {"reference": "urn:uuid:cc8158c0-c184-451b-8d1d-56ae0b98254c"}, "effectiveDateTime": "2016-05-31T12:19:17+07:00", "issued": "2016-05-31T12:19:17.553+07:00", "valueQuantity": {"value": 93.26761318782741, "unit": "kg", "system": "http://unitsofmeasure.org", "code": "kg"}}, "request": {"method": "POST", "url": "Observation"}}, {"fullUrl": "urn:uuid:75ab098d-b80f-422a-9f99-0c0d6a09ec9f", "resource": {"resourceType": "Observation", "id": "75ab098d-b80f-422a-9f99-0c0d6a09ec9f", "meta": {"profile": ["http://standardhealthrecord.org/fhir/StructureDefinition/shr-finding-Observation", "http://standardhealthrecord.org/fhir/StructureDefinition/shr-vital-VitalSign", "http://standardhealthrecord.org/fhir/StructureDefinition/shr-vital-BodyMassIndex"]}, "status": "final", "category": [{"coding": [{"system": "http://hl7.org/fhir/observation-category", "code": "vital-signs", "display": "vital-signs"}]}], "code": {"coding": [{"system": "http://loinc.org", "code": "39156-5", "display": "Body Mass Index"}], "text": "Body Mass Index"}, "subject": {"reference": "urn:uuid:3ed64677-8b2c-440c-a593-aa0e00ac2018"}, "context": {"reference": "urn:uuid:cc8158c0-c184-451b-8d1d-56ae0b98254c"}, "effectiveDateTime": "2016-05-31T12:19:17+07:00", "issued": "2016-05-31T12:19:17.553+07:00", "valueQuantity": {"value": 30.955793285783187, "unit": "kg/m2", "system": "http://unitsofmeasure.org", "code": "kg/m2"}}, "request": {"method": "POST", "url": "Observation"}}, {"fullUrl": "urn:uuid:3500cbfb-46f7-417d-8abe-740207fc3dc5", "resource": {"resourceType": "Observation", "id": "3500cbfb-46f7-417d-8abe-740207fc3dc5", "meta": {"profile": ["http://standardhealthrecord.org/fhir/StructureDefinition/shr-finding-Observation", "http://standardhealthrecord.org/fhir/StructureDefinition/shr-vital-VitalSign", "http://standardhealthrecord.org/fhir/StructureDefinition/shr-vital-BloodPressure"]}, "status": "final", "category": [{"coding": [{"system": "http://hl7.org/fhir/observation-category", "code": "vital-signs", "display": "vital-signs"}]}], "code": {"coding": [{"system": "http://loinc.org", "code": "55284-4", "display": "Blood Pressure"}], "text": "Blood Pressure"}, "subject": {"reference": "urn:uuid:3ed64677-8b2c-440c-a593-aa0e00ac2018"}, "context": {"reference": "urn:uuid:cc8158c0-c184-451b-8d1d-56ae0b98254c"}, "effectiveDateTime": "2016-05-31T12:19:17+07:00", "issued": "2016-05-31T12:19:17.553+07:00", "component": [{"code": {"coding": [{"system": "http://loinc.org", "code": "8462-4", "display": "Diastolic Blood Pressure"}], "text": "Diastolic Blood Pressure"}, "valueQuantity": {"value": 82.03118305387304, "unit": "mmHg", "system": "http://unitsofmeasure.org", "code": "mmHg"}}, {"code": {"coding": [{"system": "http://loinc.org", "code": "8480-6", "display": "Systolic Blood Pressure"}], "text": "Systolic Blood Pressure"}, "valueQuantity": {"value": 102.54885960929617, "unit": "mmHg", "system": "http://unitsofmeasure.org", "code": "mmHg"}}]}, "request": {"method": "POST", "url": "Observation"}}, {"fullUrl": "urn:uuid:9a0b6376-1d28-407f-9b49-23eeb86ffa4c", "resource": {"resourceType": "Observation", "id": "9a0b6376-1d28-407f-9b49-23eeb86ffa4c", "meta": {"profile": ["http://standardhealthrecord.org/fhir/StructureDefinition/shr-finding-Observation"]}, "status": "final", "category": [{"coding": [{"system": "http://hl7.org/fhir/observation-category", "code": "laboratory", "display": "laboratory"}]}], "code": {"coding": [{"system": "http://loinc.org", "code": "2339-0", "display": "Glucose"}], "text": "Glucose"}, "subject": {"reference": "urn:uuid:3ed64677-8b2c-440c-a593-aa0e00ac2018"}, "context": {"reference": "urn:uuid:cc8158c0-c184-451b-8d1d-56ae0b98254c"}, "effectiveDateTime": "2016-05-31T12:19:17+07:00", "issued": "2016-05-31T12:19:17.553+07:00", "valueQuantity": {"value": 73.8587117777806, "unit": "mg/dL", "system": "http://unitsofmeasure.org", "code": "mg/dL"}}, "request": {"method": "POST", "url": "Observation"}}, {"fullUrl": "urn:uuid:fc9326a4-137d-4ad8-a1eb-18c477b00579", "resource": {"resourceType": "Observation", "id": "fc9326a4-137d-4ad8-a1eb-18c477b00579", "meta": {"profile": ["http://standardhealthrecord.org/fhir/StructureDefinition/shr-finding-Observation"]}, "status": "final", "category": [{"coding": [{"system": "http://hl7.org/fhir/observation-category", "code": "laboratory", "display": "laboratory"}]}], "code": {"coding": [{"system": "http://loinc.org", "code": "6299-2", "display": "Urea Nitrogen"}], "text": "Urea Nitrogen"}, "subject": {"reference": "urn:uuid:3ed64677-8b2c-440c-a593-aa0e00ac2018"}, "context": {"reference": "urn:uuid:cc8158c0-c184-451b-8d1d-56ae0b98254c"}, "effectiveDateTime": "2016-05-31T12:19:17+07:00", "issued": "2016-05-31T12:19:17.553+07:00", "valueQuantity": {"value": 19.134272816826545, "unit": "mg/dL", "system": "http://unitsofmeasure.org", "code": "mg/dL"}}, "request": {"method": "POST", "url": "Observation"}}, {"fullUrl": "urn:uuid:18651e76-fd2b-4f9e-bbef-6e9374046cf2", "resource": {"resourceType": "Observation", "id": "18651e76-fd2b-4f9e-bbef-6e9374046cf2", "meta": {"profile": ["http://standardhealthrecord.org/fhir/StructureDefinition/shr-finding-Observation"]}, "status": "final", "category": [{"coding": [{"system": "http://hl7.org/fhir/observation-category", "code": "laboratory", "display": "laboratory"}]}], "code": {"coding": [{"system": "http://loinc.org", "code": "38483-4", "display": "Creatinine"}], "text": "Creatinine"}, "subject": {"reference": "urn:uuid:3ed64677-8b2c-440c-a593-aa0e00ac2018"}, "context": {"reference": "urn:uuid:cc8158c0-c184-451b-8d1d-56ae0b98254c"}, "effectiveDateTime": "2016-05-31T12:19:17+07:00", "issued": "2016-05-31T12:19:17.553+07:00", "valueQuantity": {"value": 1.578914034756253, "unit": "mg/dL", "system": "http://unitsofmeasure.org", "code": "mg/dL"}}, "request": {"method": "POST", "url": "Observation"}}, {"fullUrl": "urn:uuid:223be36d-fdc1-4535-8158-dfa05a39ba5b", "resource": {"resourceType": "Observation", "id": "223be36d-fdc1-4535-8158-dfa05a39ba5b", "meta": {"profile": ["http://standardhealthrecord.org/fhir/StructureDefinition/shr-finding-Observation"]}, "status": "final", "category": [{"coding": [{"system": "http://hl7.org/fhir/observation-category", "code": "laboratory", "display": "laboratory"}]}], "code": {"coding": [{"system": "http://loinc.org", "code": "49765-1", "display": "Calcium"}], "text": "Calcium"}, "subject": {"reference": "urn:uuid:3ed64677-8b2c-440c-a593-aa0e00ac2018"}, "context": {"reference": "urn:uuid:cc8158c0-c184-451b-8d1d-56ae0b98254c"}, "effectiveDateTime": "2016-05-31T12:19:17+07:00", "issued": "2016-05-31T12:19:17.553+07:00", "valueQuantity": {"value": 9.9619948925308, "unit": "mg/dL", "system": "http://unitsofmeasure.org", "code": "mg/dL"}}, "request": {"method": "POST", "url": "Observation"}}, {"fullUrl": "urn:uuid:bc119565-e41f-44ef-adf6-53c8827ff4e7", "resource": {"resourceType": "Observation", "id": "bc119565-e41f-44ef-adf6-53c8827ff4e7", "meta": {"profile": ["http://standardhealthrecord.org/fhir/StructureDefinition/shr-finding-Observation"]}, "status": "final", "category": [{"coding": [{"system": "http://hl7.org/fhir/observation-category", "code": "laboratory", "display": "laboratory"}]}], "code": {"coding": [{"system": "http://loinc.org", "code": "2947-0", "display": "Sodium"}], "text": "Sodium"}, "subject": {"reference": "urn:uuid:3ed64677-8b2c-440c-a593-aa0e00ac2018"}, "context": {"reference": "urn:uuid:cc8158c0-c184-451b-8d1d-56ae0b98254c"}, "effectiveDateTime": "2016-05-31T12:19:17+07:00", "issued": "2016-05-31T12:19:17.553+07:00", "valueQuantity": {"value": 142.50607919015417, "unit": "mmol/L", "system": "http://unitsofmeasure.org", "code": "mmol/L"}}, "request": {"method": "POST", "url": "Observation"}}, {"fullUrl": "urn:uuid:349c8208-cd82-4f6a-9f4b-2b97e388b7a9", "resource": {"resourceType": "Observation", "id": "349c8208-cd82-4f6a-9f4b-2b97e388b7a9", "meta": {"profile": ["http://standardhealthrecord.org/fhir/StructureDefinition/shr-finding-Observation"]}, "status": "final", "category": [{"coding": [{"system": "http://hl7.org/fhir/observation-category", "code": "laboratory", "display": "laboratory"}]}], "code": {"coding": [{"system": "http://loinc.org", "code": "6298-4", "display": "Potassium"}], "text": "Potassium"}, "subject": {"reference": "urn:uuid:3ed64677-8b2c-440c-a593-aa0e00ac2018"}, "context": {"reference": "urn:uuid:cc8158c0-c184-451b-8d1d-56ae0b98254c"}, "effectiveDateTime": "2016-05-31T12:19:17+07:00", "issued": "2016-05-31T12:19:17.553+07:00", "valueQuantity": {"value": 5.097356037866785, "unit": "mmol/L", "system": "http://unitsofmeasure.org", "code": "mmol/L"}}, "request": {"method": "POST", "url": "Observation"}}, {"fullUrl": "urn:uuid:55da3d6d-b879-475e-908c-9fa4cf955bc6", "resource": {"resourceType": "Observation", "id": "55da3d6d-b879-475e-908c-9fa4cf955bc6", "meta": {"profile": ["http://standardhealthrecord.org/fhir/StructureDefinition/shr-finding-Observation"]}, "status": "final", "category": [{"coding": [{"system": "http://hl7.org/fhir/observation-category", "code": "laboratory", "display": "laboratory"}]}], "code": {"coding": [{"system": "http://loinc.org", "code": "2069-3", "display": "Chloride"}], "text": "Chloride"}, "subject": {"reference": "urn:uuid:3ed64677-8b2c-440c-a593-aa0e00ac2018"}, "context": {"reference": "urn:uuid:cc8158c0-c184-451b-8d1d-56ae0b98254c"}, "effectiveDateTime": "2016-05-31T12:19:17+07:00", "issued": "2016-05-31T12:19:17.553+07:00", "valueQuantity": {"value": 103.79655531416311, "unit": "mmol/L", "system": "http://unitsofmeasure.org", "code": "mmol/L"}}, "request": {"method": "POST", "url": "Observation"}}, {"fullUrl": "urn:uuid:a2dd8edd-86e6-466b-8f8f-044096e4862b", "resource": {"resourceType": "Observation", "id": "a2dd8edd-86e6-466b-8f8f-044096e4862b", "meta": {"profile": ["http://standardhealthrecord.org/fhir/StructureDefinition/shr-finding-Observation"]}, "status": "final", "category": [{"coding": [{"system": "http://hl7.org/fhir/observation-category", "code": "laboratory", "display": "laboratory"}]}], "code": {"coding": [{"system": "http://loinc.org", "code": "20565-8", "display": "Carbon Dioxide"}], "text": "Carbon Dioxide"}, "subject": {"reference": "urn:uuid:3ed64677-8b2c-440c-a593-aa0e00ac2018"}, "context": {"reference": "urn:uuid:cc8158c0-c184-451b-8d1d-56ae0b98254c"}, "effectiveDateTime": "2016-05-31T12:19:17+07:00", "issued": "2016-05-31T12:19:17.553+07:00", "valueQuantity": {"value": 25.072768790079905, "unit": "mmol/L", "system": "http://unitsofmeasure.org", "code": "mmol/L"}}, "request": {"method": "POST", "url": "Observation"}}, {"fullUrl": "urn:uuid:b7af6404-74f5-4e54-9df8-a2b432bef778", "resource": {"resourceType": "Observation", "id": "b7af6404-74f5-4e54-9df8-a2b432bef778", "meta": {"profile": ["http://standardhealthrecord.org/fhir/StructureDefinition/shr-finding-Observation"]}, "status": "final", "category": [{"coding": [{"system": "http://hl7.org/fhir/observation-category", "code": "laboratory", "display": "laboratory"}]}], "code": {"coding": [{"system": "http://loinc.org", "code": "2093-3", "display": "Total Cholesterol"}], "text": "Total Cholesterol"}, "subject": {"reference": "urn:uuid:3ed64677-8b2c-440c-a593-aa0e00ac2018"}, "context": {"reference": "urn:uuid:cc8158c0-c184-451b-8d1d-56ae0b98254c"}, "effectiveDateTime": "2016-05-31T12:19:17+07:00", "issued": "2016-05-31T12:19:17.553+07:00", "valueQuantity": {"value": 176.0764531233626, "unit": "mg/dL", "system": "http://unitsofmeasure.org", "code": "mg/dL"}}, "request": {"method": "POST", "url": "Observation"}}, {"fullUrl": "urn:uuid:63ad5a88-d2b1-4488-8676-36c5646508f4", "resource": {"resourceType": "Observation", "id": "63ad5a88-d2b1-4488-8676-36c5646508f4", "meta": {"profile": ["http://standardhealthrecord.org/fhir/StructureDefinition/shr-finding-Observation"]}, "status": "final", "category": [{"coding": [{"system": "http://hl7.org/fhir/observation-category", "code": "laboratory", "display": "laboratory"}]}], "code": {"coding": [{"system": "http://loinc.org", "code": "2571-8", "display": "Triglycerides"}], "text": "Triglycerides"}, "subject": {"reference": "urn:uuid:3ed64677-8b2c-440c-a593-aa0e00ac2018"}, "context": {"reference": "urn:uuid:cc8158c0-c184-451b-8d1d-56ae0b98254c"}, "effectiveDateTime": "2016-05-31T12:19:17+07:00", "issued": "2016-05-31T12:19:17.553+07:00", "valueQuantity": {"value": 132.99096624938971, "unit": "mg/dL", "system": "http://unitsofmeasure.org", "code": "mg/dL"}}, "request": {"method": "POST", "url": "Observation"}}, {"fullUrl": "urn:uuid:52c2127f-bfb6-4963-958e-cfda1872d50b", "resource": {"resourceType": "Observation", "id": "52c2127f-bfb6-4963-958e-cfda1872d50b", "meta": {"profile": ["http://standardhealthrecord.org/fhir/StructureDefinition/shr-finding-Observation"]}, "status": "final", "category": [{"coding": [{"system": "http://hl7.org/fhir/observation-category", "code": "laboratory", "display": "laboratory"}]}], "code": {"coding": [{"system": "http://loinc.org", "code": "18262-6", "display": "Low Density Lipoprotein Cholesterol"}], "text": "Low Density Lipoprotein Cholesterol"}, "subject": {"reference": "urn:uuid:3ed64677-8b2c-440c-a593-aa0e00ac2018"}, "context": {"reference": "urn:uuid:cc8158c0-c184-451b-8d1d-56ae0b98254c"}, "effectiveDateTime": "2016-05-31T12:19:17+07:00", "issued": "2016-05-31T12:19:17.553+07:00", "valueQuantity": {"value": 82.45681961279988, "unit": "mg/dL", "system": "http://unitsofmeasure.org", "code": "mg/dL"}}, "request": {"method": "POST", "url": "Observation"}}, {"fullUrl": "urn:uuid:93baf0bd-d059-4126-bcdc-145e8c48ead1", "resource": {"resourceType": "Observation", "id": "93baf0bd-d059-4126-bcdc-145e8c48ead1", "meta": {"profile": ["http://standardhealthrecord.org/fhir/StructureDefinition/shr-finding-Observation"]}, "status": "final", "category": [{"coding": [{"system": "http://hl7.org/fhir/observation-category", "code": "laboratory", "display": "laboratory"}]}], "code": {"coding": [{"system": "http://loinc.org", "code": "2085-9", "display": "High Density Lipoprotein Cholesterol"}], "text": "High Density Lipoprotein Cholesterol"}, "subject": {"reference": "urn:uuid:3ed64677-8b2c-440c-a593-aa0e00ac2018"}, "context": {"reference": "urn:uuid:cc8158c0-c184-451b-8d1d-56ae0b98254c"}, "effectiveDateTime": "2016-05-31T12:19:17+07:00", "issued": "2016-05-31T12:19:17.553+07:00", "valueQuantity": {"value": 67.02144026068478, "unit": "mg/dL", "system": "http://unitsofmeasure.org", "code": "mg/dL"}}, "request": {"method": "POST", "url": "Observation"}}, {"fullUrl": "urn:uuid:68fad17d-195f-493d-90be-e1b7eb5c2a06", "resource": {"resourceType": "Observation", "id": "68fad17d-195f-493d-90be-e1b7eb5c2a06", "meta": {"profile": ["http://standardhealthrecord.org/fhir/StructureDefinition/shr-finding-Observation"]}, "status": "final", "category": [{"coding": [{"system": "http://hl7.org/fhir/observation-category", "code": "survey", "display": "survey"}]}], "code": {"coding": [{"system": "http://loinc.org", "code": "72166-2", "display": "Tobacco smoking status NHIS"}], "text": "Tobacco smoking status NHIS"}, "subject": {"reference": "urn:uuid:3ed64677-8b2c-440c-a593-aa0e00ac2018"}, "context": {"reference": "urn:uuid:cc8158c0-c184-451b-8d1d-56ae0b98254c"}, "effectiveDateTime": "2016-05-31T12:19:17+07:00", "issued": "2016-05-31T12:19:17.553+07:00", "valueCodeableConcept": {"coding": [{"system": "http://snomed.info/sct", "code": "266919005", "display": "Never smoker"}], "text": "Never smoker"}}, "request": {"method": "POST", "url": "Observation"}}, {"fullUrl": "urn:uuid:c66b53c7-65f6-4c8e-9d3c-82226623c652", "resource": {"resourceType": "Observation", "id": "c66b53c7-65f6-4c8e-9d3c-82226623c652", "meta": {"profile": ["http://standardhealthrecord.org/fhir/StructureDefinition/shr-finding-Observation"]}, "status": "final", "category": [{"coding": [{"system": "http://hl7.org/fhir/observation-category", "code": "laboratory", "display": "laboratory"}]}], "code": {"coding": [{"system": "http://loinc.org", "code": "4548-4", "display": "Hemoglobin A1c/Hemoglobin.total in Blood"}], "text": "Hemoglobin A1c/Hemoglobin.total in Blood"}, "subject": {"reference": "urn:uuid:3ed64677-8b2c-440c-a593-aa0e00ac2018"}, "context": {"reference": "urn:uuid:cc8158c0-c184-451b-8d1d-56ae0b98254c"}, "effectiveDateTime": "2016-05-31T12:19:17+07:00", "issued": "2016-05-31T12:19:17.553+07:00", "valueQuantity": {"value": 5.847121049873947, "unit": "%", "system": "http://unitsofmeasure.org", "code": "%"}}, "request": {"method": "POST", "url": "Observation"}}, {"fullUrl": "urn:uuid:c4372a3a-0b52-4a8a-926f-d5438f289e51", "resource": {"resourceType": "Immunization", "id": "c4372a3a-0b52-4a8a-926f-d5438f289e51", "meta": {"profile": ["http://standardhealthrecord.org/fhir/StructureDefinition/shr-immunization-ImmunizationGiven"]}, "extension": [{"url": "http://standardhealthrecord.org/fhir/StructureDefinition/shr-action-PerformedContext-extension", "extension": [{"url": "http://standardhealthrecord.org/fhir/StructureDefinition/shr-action-Status-extension", "valueCode": "completed"}]}], "status": "completed", "notGiven": false, "vaccineCode": {"coding": [{"system": "http://hl7.org/fhir/sid/cvx", "code": "140", "display": "Influenza, seasonal, injectable, preservative free"}], "text": "Influenza, seasonal, injectable, preservative free"}, "patient": {"reference": "urn:uuid:3ed64677-8b2c-440c-a593-aa0e00ac2018"}, "encounter": {"reference": "urn:uuid:cc8158c0-c184-451b-8d1d-56ae0b98254c"}, "date": "2016-05-31T12:19:17+07:00", "primarySource": true}, "request": {"method": "POST", "url": "Immunization"}}, {"fullUrl": "urn:uuid:443a1761-a964-4371-ae55-b1b6793d9b61", "resource": {"resourceType": "DiagnosticReport", "id": "443a1761-a964-4371-ae55-b1b6793d9b61", "status": "final", "code": {"coding": [{"system": "http://loinc.org", "code": "51990-0", "display": "Basic Metabolic Panel"}], "text": "Basic Metabolic Panel"}, "subject": {"reference": "urn:uuid:3ed64677-8b2c-440c-a593-aa0e00ac2018"}, "context": {"reference": "urn:uuid:cc8158c0-c184-451b-8d1d-56ae0b98254c"}, "effectiveDateTime": "2016-05-31T12:19:17+07:00", "issued": "2016-05-31T12:19:17.553+07:00", "result": [{"reference": "urn:uuid:9a0b6376-1d28-407f-9b49-23eeb86ffa4c", "display": "Glucose"}, {"reference": "urn:uuid:fc9326a4-137d-4ad8-a1eb-18c477b00579", "display": "Urea Nitrogen"}, {"reference": "urn:uuid:18651e76-fd2b-4f9e-bbef-6e9374046cf2", "display": "Creatinine"}, {"reference": "urn:uuid:223be36d-fdc1-4535-8158-dfa05a39ba5b", "display": "Calcium"}, {"reference": "urn:uuid:bc119565-e41f-44ef-adf6-53c8827ff4e7", "display": "Sodium"}, {"reference": "urn:uuid:349c8208-cd82-4f6a-9f4b-2b97e388b7a9", "display": "Potassium"}, {"reference": "urn:uuid:55da3d6d-b879-475e-908c-9fa4cf955bc6", "display": "Chloride"}, {"reference": "urn:uuid:a2dd8edd-86e6-466b-8f8f-044096e4862b", "display": "Carbon Dioxide"}]}, "request": {"method": "POST", "url": "DiagnosticReport"}}, {"fullUrl": "urn:uuid:5872507f-0b16-4712-8c74-a7a6af14a907", "resource": {"resourceType": "DiagnosticReport", "id": "5872507f-0b16-4712-8c74-a7a6af14a907", "status": "final", "code": {"coding": [{"system": "http://loinc.org", "code": "57698-3", "display": "Lipid Panel"}], "text": "Lipid Panel"}, "subject": {"reference": "urn:uuid:3ed64677-8b2c-440c-a593-aa0e00ac2018"}, "context": {"reference": "urn:uuid:cc8158c0-c184-451b-8d1d-56ae0b98254c"}, "effectiveDateTime": "2016-05-31T12:19:17+07:00", "issued": "2016-05-31T12:19:17.553+07:00", "result": [{"reference": "urn:uuid:b7af6404-74f5-4e54-9df8-a2b432bef778", "display": "Total Cholesterol"}, {"reference": "urn:uuid:63ad5a88-d2b1-4488-8676-36c5646508f4", "display": "Triglycerides"}, {"reference": "urn:uuid:52c2127f-bfb6-4963-958e-cfda1872d50b", "display": "Low Density Lipoprotein Cholesterol"}, {"reference": "urn:uuid:93baf0bd-d059-4126-bcdc-145e8c48ead1", "display": "High Density Lipoprotein Cholesterol"}]}, "request": {"method": "POST", "url": "DiagnosticReport"}}, {"fullUrl": "urn:uuid:268dc838-7b55-4981-9453-a8e937359ca0", "resource": {"resourceType": "Claim", "id": "268dc838-7b55-4981-9453-a8e937359ca0", "status": "active", "use": "complete", "patient": {"reference": "urn:uuid:3ed64677-8b2c-440c-a593-aa0e00ac2018"}, "billablePeriod": {"start": "2016-05-31T12:19:17+07:00", "end": "2016-05-31T12:34:17+07:00"}, "organization": {"reference": "urn:uuid:609c86d7-5324-477b-99a2-b1608551ef1f"}, "information": [{"sequence": 1, "category": {"coding": [{"system": "http://hl7.org/fhir/claiminformationcategory", "code": "info"}]}, "valueReference": {"reference": "urn:uuid:c4372a3a-0b52-4a8a-926f-d5438f289e51"}}], "item": [{"sequence": 1, "encounter": [{"reference": "urn:uuid:cc8158c0-c184-451b-8d1d-56ae0b98254c"}]}, {"sequence": 2, "informationLinkId": [1], "net": {"value": 140.52, "system": "urn:iso:std:iso:4217", "code": "USD"}}], "total": {"value": 265.52, "system": "urn:iso:std:iso:4217", "code": "USD"}}, "request": {"method": "POST", "url": "Claim"}}, {"fullUrl": "urn:uuid:47ccf8ef-448d-461f-9f6a-8a26795a9c7f", "resource": {"resourceType": "Encounter", "id": "47ccf8ef-448d-461f-9f6a-8a26795a9c7f", "meta": {"profile": ["http://standardhealthrecord.org/fhir/StructureDefinition/shr-encounter-EncounterPerformed"]}, "extension": [{"url": "http://standardhealthrecord.org/fhir/StructureDefinition/shr-action-PerformedContext-extension", "extension": [{"url": "http://standardhealthrecord.org/fhir/StructureDefinition/shr-action-Status-extension", "valueCode": "finished"}]}], "status": "finished", "class": {"code": "ambulatory"}, "type": [{"coding": [{"system": "http://snomed.info/sct", "code": "185345009", "display": "Encounter for symptom"}], "text": "Encounter for symptom"}], "subject": {"reference": "urn:uuid:3ed64677-8b2c-440c-a593-aa0e00ac2018"}, "period": {"start": "2017-03-18T12:19:17+07:00", "end": "2017-03-18T12:34:17+07:00"}, "reason": [{"coding": [{"system": "http://snomed.info/sct", "code": "444814009", "display": "Viral sinusitis (disorder)"}]}], "serviceProvider": {"reference": "urn:uuid:609c86d7-5324-477b-99a2-b1608551ef1f"}}, "request": {"method": "POST", "url": "Encounter"}}, {"fullUrl": "urn:uuid:0ce8baef-3be4-481b-8bb5-1e935cd95a48", "resource": {"resourceType": "Condition", "id": "0ce8baef-3be4-481b-8bb5-1e935cd95a48", "meta": {"profile": ["http://standardhealthrecord.org/fhir/StructureDefinition/shr-condition-Condition"]}, "clinicalStatus": "resolved", "verificationStatus": "confirmed", "category": [{"coding": [{"system": "http://standardhealthrecord.org/shr/condition/vs/ConditionCategoryVS", "code": "disease", "display": "Disease"}]}], "code": {"coding": [{"system": "http://snomed.info/sct", "code": "444814009", "display": "Viral sinusitis (disorder)"}], "text": "Viral sinusitis (disorder)"}, "subject": {"reference": "urn:uuid:3ed64677-8b2c-440c-a593-aa0e00ac2018"}, "context": {"reference": "urn:uuid:47ccf8ef-448d-461f-9f6a-8a26795a9c7f"}, "onsetDateTime": "2017-03-18T12:19:17+07:00", "abatementDateTime": "2017-04-08T12:19:17+07:00", "assertedDate": "2017-03-18T12:19:17+07:00"}, "request": {"method": "POST", "url": "Condition"}}, {"fullUrl": "urn:uuid:74249bda-f331-4ed1-af36-7b55e730cee7", "resource": {"resourceType": "Claim", "id": "74249bda-f331-4ed1-af36-7b55e730cee7", "status": "active", "use": "complete", "patient": {"reference": "urn:uuid:3ed64677-8b2c-440c-a593-aa0e00ac2018"}, "billablePeriod": {"start": "2017-03-18T12:19:17+07:00", "end": "2017-03-18T12:34:17+07:00"}, "organization": {"reference": "urn:uuid:609c86d7-5324-477b-99a2-b1608551ef1f"}, "diagnosis": [{"sequence": 1, "diagnosisReference": {"reference": "urn:uuid:0ce8baef-3be4-481b-8bb5-1e935cd95a48"}}], "item": [{"sequence": 1, "encounter": [{"reference": "urn:uuid:47ccf8ef-448d-461f-9f6a-8a26795a9c7f"}]}, {"sequence": 2, "diagnosisLinkId": [1]}], "total": {"value": 125.0, "system": "urn:iso:std:iso:4217", "code": "USD"}}, "request": {"method": "POST", "url": "Claim"}}, {"fullUrl": "urn:uuid:dc02f29b-c186-4542-84a0-4101ea8d742f", "resource": {"resourceType": "Encounter", "id": "dc02f29b-c186-4542-84a0-4101ea8d742f", "meta": {"profile": ["http://standardhealthrecord.org/fhir/StructureDefinition/shr-encounter-EncounterPerformed"]}, "extension": [{"url": "http://standardhealthrecord.org/fhir/StructureDefinition/shr-action-PerformedContext-extension", "extension": [{"url": "http://standardhealthrecord.org/fhir/StructureDefinition/shr-action-Status-extension", "valueCode": "finished"}]}], "status": "finished", "class": {"code": "ambulatory"}, "type": [{"coding": [{"system": "http://snomed.info/sct", "code": "185345009", "display": "Encounter for symptom"}], "text": "Encounter for symptom"}], "subject": {"reference": "urn:uuid:3ed64677-8b2c-440c-a593-aa0e00ac2018"}, "period": {"start": "2017-06-16T12:19:17+07:00", "end": "2017-06-16T12:34:17+07:00"}, "reason": [{"coding": [{"system": "http://snomed.info/sct", "code": "444814009", "display": "Viral sinusitis (disorder)"}]}], "serviceProvider": {"reference": "urn:uuid:609c86d7-5324-477b-99a2-b1608551ef1f"}}, "request": {"method": "POST", "url": "Encounter"}}, {"fullUrl": "urn:uuid:2277896a-d1b5-47d0-bffe-58c46e64d64a", "resource": {"resourceType": "Condition", "id": "2277896a-d1b5-47d0-bffe-58c46e64d64a", "meta": {"profile": ["http://standardhealthrecord.org/fhir/StructureDefinition/shr-condition-Condition"]}, "clinicalStatus": "resolved", "verificationStatus": "confirmed", "category": [{"coding": [{"system": "http://standardhealthrecord.org/shr/condition/vs/ConditionCategoryVS", "code": "disease", "display": "Disease"}]}], "code": {"coding": [{"system": "http://snomed.info/sct", "code": "444814009", "display": "Viral sinusitis (disorder)"}], "text": "Viral sinusitis (disorder)"}, "subject": {"reference": "urn:uuid:3ed64677-8b2c-440c-a593-aa0e00ac2018"}, "context": {"reference": "urn:uuid:dc02f29b-c186-4542-84a0-4101ea8d742f"}, "onsetDateTime": "2017-06-16T12:19:17+07:00", "abatementDateTime": "2017-06-23T12:19:17+07:00", "assertedDate": "2017-06-16T12:19:17+07:00"}, "request": {"method": "POST", "url": "Condition"}}, {"fullUrl": "urn:uuid:31535aac-775c-4b1d-bc91-339cf7bf07f1", "resource": {"resourceType": "Claim", "id": "31535aac-775c-4b1d-bc91-339cf7bf07f1", "status": "active", "use": "complete", "patient": {"reference": "urn:uuid:3ed64677-8b2c-440c-a593-aa0e00ac2018"}, "billablePeriod": {"start": "2017-06-16T12:19:17+07:00", "end": "2017-06-16T12:34:17+07:00"}, "organization": {"reference": "urn:uuid:609c86d7-5324-477b-99a2-b1608551ef1f"}, "diagnosis": [{"sequence": 1, "diagnosisReference": {"reference": "urn:uuid:2277896a-d1b5-47d0-bffe-58c46e64d64a"}}], "item": [{"sequence": 1, "encounter": [{"reference": "urn:uuid:dc02f29b-c186-4542-84a0-4101ea8d742f"}]}, {"sequence": 2, "diagnosisLinkId": [1]}], "total": {"value": 125.0, "system": "urn:iso:std:iso:4217", "code": "USD"}}, "request": {"method": "POST", "url": "Claim"}}]}